[{"id":49057,"game_id":21401126,"team_id":1610612756,"opponent_id":1610612744,"player_id":202077,"box_minutes":168,"box_fgm":1,"box_fga":2,"box_fg3m":0,"box_fg3a":1,"box_ftm":0,"box_fta":0,"box_oreb":0,"box_dreb":0,"box_ast":0,"box_stl":0,"box_blk":0,"box_to":0,"box_pf":2,"box_pts":2,"box_plus_minus":0,"trk_speed":"4.99","trk_dist":"0.23","trk_orbc":0,"trk_drbc":0,"trk_touches":9,"trk_sast":0,"trk_ftast":0,"trk_pass":7,"trk_cfgm":1,"trk_cfga":1,"trk_ufgm":0,"trk_ufga":1,"trk_dfgm":0,"trk_dfga":0,"adv_off_rating":"66.7","adv_def_rating":"69.4","adv_ast_pct":"0.000","adv_ast_tov":"0.000","adv_ast_ratio":"0.00","adv_oreb_pct":"0.000","adv_dreb_pct":"0.000","adv_treb_pct":"0.000","adv_tm_tov_pct":"0.0","adv_efg_pct":"0.500","adv_ts_pct":"0.500","adv_usg_pct":"0.333","adv_pace":"100.80","adv_pie":"-0.154","misc_pts_off_tov":0,"misc_pts_2nd_chance":0,"misc_pts_fb":0,"misc_pts_paint":0,"misc_opp_pts_off_tov":0,"misc_opp_pts_2nd_chance":0,"misc_opp_pts_fb":2,"misc_opp_pts_paint":0,"misc_blk":0,"misc_blka":0,"misc_pf":2,"misc_pfd":0,"scr_pct_2pt_fga":"0.500","scr_pct_pts_2pt":"1.000","scr_pct_pts_2ptmr":"1.000","scr_pct_pts_3pt":"0.000","scr_pct_pts_fb":"0.000","scr_pct_pts_ft":"0.000","scr_pct_pts_off_tov":"0.000","scr_pct_pts_paint":"0.000","scr_pct_pts_ast_2pm":"1.000","scr_pct_pts_ast_3pm":"0.000","scr_pct_pts_ast_fgm":"1.000","usg_pct":"0.333","usg_pct_fgm":"0.500","usg_pct_fga":"0.400","usg_pct_fg3m":"0.000","usg_pct_fg3a":"1.000","usg_pct_ftm":"0.000","usg_pct_fta":"0.000","usg_pct_oreb":"0.000","usg_pct_dreb":"0.000","usg_pct_reb":"0.000","usg_pct_ast":"0.000","usg_pct_stl":"0.000","usg_pct_tov":"0.000","usg_pct_blk":"0.000","usg_pct_blka":"0.000","usg_pct_pf":"0.667","usg_pct_pfd":"0.000","usg_pct_pts":"0.500","four_efg_pct":"0.400","four_fta_rate":"0.000","four_tm_tov_pct":"0.167","four_oreb_pct":"0.000","four_opp_efg_pct":"0.000","four_opp_fta_rate":"0.800","four_opp_tm_tov_pct":"0.000","four_opp_oreb_pct":"0.200"},{"id":49465,"game_id":21401145,"team_id":1610612756,"opponent_id":1610612762,"player_id":202077,"box_minutes":612,"box_fgm":0,"box_fga":2,"box_fg3m":0,"box_fg3a":0,"box_ftm":0,"box_fta":0,"box_oreb":0,"box_dreb":1,"box_ast":1,"box_stl":0,"box_blk":1,"box_to":2,"box_pf":2,"box_pts":0,"box_plus_minus":0,"trk_speed":"4.17","trk_dist":"0.71","trk_orbc":0,"trk_drbc":2,"trk_touches":23,"trk_sast":0,"trk_ftast":2,"trk_pass":18,"trk_cfgm":0,"trk_cfga":0,"trk_ufgm":0,"trk_ufga":2,"trk_dfgm":1,"trk_dfga":1,"adv_off_rating":"94.5","adv_def_rating":"95.9","adv_ast_pct":"0.333","adv_ast_tov":"0.500","adv_ast_ratio":"20.00","adv_oreb_pct":"0.000","adv_dreb_pct":"0.143","adv_treb_pct":"0.071","adv_tm_tov_pct":"40.0","adv_efg_pct":"0.000","adv_ts_pct":"0.000","adv_usg_pct":"0.200","adv_pace":"88.94","adv_pie":"-0.206","misc_pts_off_tov":0,"misc_pts_2nd_chance":0,"misc_pts_fb":0,"misc_pts_paint":0,"misc_opp_pts_off_tov":2,"misc_opp_pts_2nd_chance":6,"misc_opp_pts_fb":0,"misc_opp_pts_paint":6,"misc_blk":1,"misc_blka":0,"misc_pf":2,"misc_pfd":0,"scr_pct_2pt_fga":"1.000","scr_pct_pts_2pt":"0.000","scr_pct_pts_2ptmr":"0.000","scr_pct_pts_3pt":"0.000","scr_pct_pts_fb":"0.000","scr_pct_pts_ft":"0.000","scr_pct_pts_off_tov":"0.000","scr_pct_pts_paint":"0.000","scr_pct_pts_ast_2pm":"0.000","scr_pct_pts_ast_3pm":"0.000","scr_pct_pts_ast_fgm":"0.000","usg_pct":"0.200","usg_pct_fgm":"0.000","usg_pct_fga":"0.286","usg_pct_fg3m":"0.000","usg_pct_fg3a":"0.000","usg_pct_ftm":"0.000","usg_pct_fta":"0.000","usg_pct_oreb":"0.000","usg_pct_dreb":"0.333","usg_pct_reb":"0.250","usg_pct_ast":"0.500","usg_pct_stl":"0.000","usg_pct_tov":"0.333","usg_pct_blk":"1.000","usg_pct_blka":"0.000","usg_pct_pf":"0.400","usg_pct_pfd":"0.000","usg_pct_pts":"0.000","four_efg_pct":"0.429","four_fta_rate":"2.286","four_tm_tov_pct":"0.315","four_oreb_pct":"0.143","four_opp_efg_pct":"0.438","four_opp_fta_rate":"0.250","four_opp_tm_tov_pct":"0.267","four_opp_oreb_pct":"0.571"},{"id":50134,"game_id":21401182,"team_id":1610612756,"opponent_id":1610612740,"player_id":202077,"box_minutes":110,"box_fgm":0,"box_fga":1,"box_fg3m":0,"box_fg3a":0,"box_ftm":0,"box_fta":0,"box_oreb":0,"box_dreb":0,"box_ast":1,"box_stl":0,"box_blk":0,"box_to":0,"box_pf":0,"box_pts":0,"box_plus_minus":2,"trk_speed":"3.19","trk_dist":"0.10","trk_orbc":0,"trk_drbc":0,"trk_touches":6,"trk_sast":0,"trk_ftast":0,"trk_pass":4,"trk_cfgm":0,"trk_cfga":1,"trk_ufgm":0,"trk_ufga":0,"trk_dfgm":0,"trk_dfga":0,"adv_off_rating":"100.0","adv_def_rating":"82.0","adv_ast_pct":"0.500","adv_ast_tov":"0.000","adv_ast_ratio":"50.00","adv_oreb_pct":"0.000","adv_dreb_pct":"0.000","adv_treb_pct":"0.000","adv_tm_tov_pct":"0.0","adv_efg_pct":"0.000","adv_ts_pct":"0.000","adv_usg_pct":"0.250","adv_pace":"84.31","adv_pie":"0.000","misc_pts_off_tov":0,"misc_pts_2nd_chance":0,"misc_pts_fb":0,"misc_pts_paint":0,"misc_opp_pts_off_tov":0,"misc_opp_pts_2nd_chance":0,"misc_opp_pts_fb":0,"misc_opp_pts_paint":2,"misc_blk":0,"misc_blka":1,"misc_pf":0,"misc_pfd":1,"scr_pct_2pt_fga":"1.000","scr_pct_pts_2pt":"0.000","scr_pct_pts_2ptmr":"0.000","scr_pct_pts_3pt":"0.000","scr_pct_pts_fb":"0.000","scr_pct_pts_ft":"0.000","scr_pct_pts_off_tov":"0.000","scr_pct_pts_paint":"0.000","scr_pct_pts_ast_2pm":"0.000","scr_pct_pts_ast_3pm":"0.000","scr_pct_pts_ast_fgm":"0.000","usg_pct":"0.250","usg_pct_fgm":"0.000","usg_pct_fga":"0.250","usg_pct_fg3m":"0.000","usg_pct_fg3a":"0.000","usg_pct_ftm":"0.000","usg_pct_fta":"0.000","usg_pct_oreb":"0.000","usg_pct_dreb":"0.000","usg_pct_reb":"0.000","usg_pct_ast":"0.500","usg_pct_stl":"0.000","usg_pct_tov":"0.000","usg_pct_blk":"0.000","usg_pct_blka":"1.000","usg_pct_pf":"0.000","usg_pct_pfd":"1.000","usg_pct_pts":"0.000","four_efg_pct":"0.500","four_fta_rate":"0.000","four_tm_tov_pct":"0.000","four_oreb_pct":"0.000","four_opp_efg_pct":"1.000","four_opp_fta_rate":"1.000","four_opp_tm_tov_pct":"0.410","four_opp_oreb_pct":"0.000"},{"id":50704,"game_id":21401216,"team_id":1610612756,"opponent_id":1610612746,"player_id":202077,"box_minutes":877,"box_fgm":2,"box_fga":4,"box_fg3m":1,"box_fg3a":1,"box_ftm":2,"box_fta":2,"box_oreb":0,"box_dreb":1,"box_ast":0,"box_stl":3,"box_blk":0,"box_to":2,"box_pf":1,"box_pts":7,"box_plus_minus":-2,"trk_speed":"4.11","trk_dist":"1.00","trk_orbc":1,"trk_drbc":2,"trk_touches":32,"trk_sast":0,"trk_ftast":2,"trk_pass":24,"trk_cfgm":0,"trk_cfga":2,"trk_ufgm":2,"trk_ufga":2,"trk_dfgm":0,"trk_dfga":0,"adv_off_rating":"109.2","adv_def_rating":"113.5","adv_ast_pct":"0.000","adv_ast_tov":"0.000","adv_ast_ratio":"0.00","adv_oreb_pct":"0.000","adv_dreb_pct":"0.125","adv_treb_pct":"0.048","adv_tm_tov_pct":"29.1","adv_efg_pct":"0.625","adv_ts_pct":"0.717","adv_usg_pct":"0.219","adv_pace":"94.38","adv_pie":"0.112","misc_pts_off_tov":0,"misc_pts_2nd_chance":0,"misc_pts_fb":0,"misc_pts_paint":2,"misc_opp_pts_off_tov":5,"misc_opp_pts_2nd_chance":5,"misc_opp_pts_fb":3,"misc_opp_pts_paint":10,"misc_blk":0,"misc_blka":0,"misc_pf":1,"misc_pfd":1,"scr_pct_2pt_fga":"0.750","scr_pct_pts_2pt":"0.286","scr_pct_pts_2ptmr":"0.000","scr_pct_pts_3pt":"0.429","scr_pct_pts_fb":"0.000","scr_pct_pts_ft":"0.286","scr_pct_pts_off_tov":"0.000","scr_pct_pts_paint":"0.286","scr_pct_pts_ast_2pm":"0.000","scr_pct_pts_ast_3pm":"1.000","scr_pct_pts_ast_fgm":"0.500","usg_pct":"0.219","usg_pct_fgm":"0.200","usg_pct_fga":"0.200","usg_pct_fg3m":"0.250","usg_pct_fg3a":"0.143","usg_pct_ftm":"0.286","usg_pct_fta":"0.200","usg_pct_oreb":"0.000","usg_pct_dreb":"0.167","usg_pct_reb":"0.111","usg_pct_ast":"0.000","usg_pct_stl":"0.750","usg_pct_tov":"0.286","usg_pct_blk":"0.000","usg_pct_blka":"0.000","usg_pct_pf":"0.167","usg_pct_pfd":"0.111","usg_pct_pts":"0.226","four_efg_pct":"0.600","four_fta_rate":"0.500","four_tm_tov_pct":"0.246","four_oreb_pct":"0.231","four_opp_efg_pct":"0.636","four_opp_fta_rate":"0.318","four_opp_tm_tov_pct":"0.206","four_opp_oreb_pct":"0.250"}]