[{"id":52649,"game_id":21500010,"team_id":1610612745,"opponent_id":1610612743,"player_id":1626149,"box_minutes":950,"box_fgm":4,"box_fga":4,"box_fg3m":0,"box_fg3a":0,"box_ftm":0,"box_fta":0,"box_oreb":1,"box_dreb":2,"box_ast":1,"box_stl":0,"box_blk":0,"box_to":0,"box_pf":4,"box_pts":8,"box_plus_minus":2,"trk_speed":"4.22","trk_dist":"1.12","trk_orbc":3,"trk_drbc":5,"trk_touches":16,"trk_sast":0,"trk_ftast":0,"trk_pass":11,"trk_cfgm":3,"trk_cfga":3,"trk_ufgm":1,"trk_ufga":1,"trk_dfgm":0,"trk_dfga":1,"adv_off_rating":"122.8","adv_def_rating":"113.8","adv_ast_pct":"0.091","adv_ast_tov":"0.000","adv_ast_ratio":"20.00","adv_oreb_pct":"0.067","adv_dreb_pct":"0.154","adv_treb_pct":"0.107","adv_tm_tov_pct":"0.0","adv_efg_pct":"1.000","adv_ts_pct":"1.000","adv_usg_pct":"0.118","adv_pace":"97.43","adv_pie":"0.102","misc_pts_off_tov":4,"misc_pts_2nd_chance":0,"misc_pts_fb":2,"misc_pts_paint":8,"misc_opp_pts_off_tov":0,"misc_opp_pts_2nd_chance":0,"misc_opp_pts_fb":3,"misc_opp_pts_paint":10,"misc_blk":0,"misc_blka":0,"misc_pf":4,"misc_pfd":1,"scr_pct_2pt_fga":"1.000","scr_pct_pts_2pt":"1.000","scr_pct_pts_2ptmr":"0.000","scr_pct_pts_3pt":"0.000","scr_pct_pts_fb":"0.250","scr_pct_pts_ft":"0.000","scr_pct_pts_off_tov":"0.500","scr_pct_pts_paint":"1.000","scr_pct_pts_ast_2pm":"1.000","scr_pct_pts_ast_3pm":"0.000","scr_pct_pts_ast_fgm":"1.000","usg_pct":"0.118","usg_pct_fgm":"0.267","usg_pct_fga":"0.133","usg_pct_fg3m":"0.000","usg_pct_fg3a":"0.000","usg_pct_ftm":"0.000","usg_pct_fta":"0.000","usg_pct_oreb":"0.500","usg_pct_dreb":"0.250","usg_pct_reb":"0.300","usg_pct_ast":"0.091","usg_pct_stl":"0.000","usg_pct_tov":"0.000","usg_pct_blk":"0.000","usg_pct_blka":"0.000","usg_pct_pf":"0.667","usg_pct_pfd":"0.143","usg_pct_pts":"0.205","four_efg_pct":"0.617","four_fta_rate":"0.133","four_tm_tov_pct":"0.063","four_oreb_pct":"0.133","four_opp_efg_pct":"0.620","four_opp_fta_rate":"0.320","four_opp_tm_tov_pct":"0.277","four_opp_oreb_pct":"0.385"},{"id":53095,"game_id":21500030,"team_id":1610612745,"opponent_id":1610612744,"player_id":1626149,"box_minutes":1270,"box_fgm":7,"box_fga":9,"box_fg3m":0,"box_fg3a":0,"box_ftm":3,"box_fta":5,"box_oreb":1,"box_dreb":2,"box_ast":0,"box_stl":0,"box_blk":1,"box_to":0,"box_pf":1,"box_pts":17,"box_plus_minus":-11,"trk_speed":"4.32","trk_dist":"1.52","trk_orbc":4,"trk_drbc":3,"trk_touches":31,"trk_sast":0,"trk_ftast":0,"trk_pass":21,"trk_cfgm":6,"trk_cfga":8,"trk_ufgm":1,"trk_ufga":1,"trk_dfgm":1,"trk_dfga":2,"adv_off_rating":"98.4","adv_def_rating":"126.2","adv_ast_pct":"0.000","adv_ast_tov":"0.000","adv_ast_ratio":"0.00","adv_oreb_pct":"0.050","adv_dreb_pct":"0.111","adv_treb_pct":"0.079","adv_tm_tov_pct":"0.0","adv_efg_pct":"0.778","adv_ts_pct":"0.759","adv_usg_pct":"0.221","adv_pace":"102.14","adv_pie":"0.179","misc_pts_off_tov":4,"misc_pts_2nd_chance":4,"misc_pts_fb":2,"misc_pts_paint":14,"misc_opp_pts_off_tov":8,"misc_opp_pts_2nd_chance":4,"misc_opp_pts_fb":9,"misc_opp_pts_paint":24,"misc_blk":1,"misc_blka":0,"misc_pf":1,"misc_pfd":3,"scr_pct_2pt_fga":"1.000","scr_pct_pts_2pt":"0.824","scr_pct_pts_2ptmr":"0.000","scr_pct_pts_3pt":"0.000","scr_pct_pts_fb":"0.118","scr_pct_pts_ft":"0.176","scr_pct_pts_off_tov":"0.235","scr_pct_pts_paint":"0.824","scr_pct_pts_ast_2pm":"0.571","scr_pct_pts_ast_3pm":"0.000","scr_pct_pts_ast_fgm":"0.571","usg_pct":"0.221","usg_pct_fgm":"0.412","usg_pct_fga":"0.225","usg_pct_fg3m":"0.000","usg_pct_fg3a":"0.000","usg_pct_ftm":"0.333","usg_pct_fta":"0.385","usg_pct_oreb":"0.200","usg_pct_dreb":"0.154","usg_pct_reb":"0.167","usg_pct_ast":"0.000","usg_pct_stl":"0.000","usg_pct_tov":"0.000","usg_pct_blk":"0.200","usg_pct_blka":"0.000","usg_pct_pf":"0.091","usg_pct_pfd":"0.300","usg_pct_pts":"0.378","four_efg_pct":"0.450","four_fta_rate":"0.325","four_tm_tov_pct":"0.109","four_oreb_pct":"0.250","four_opp_efg_pct":"0.566","four_opp_fta_rate":"0.500","four_opp_tm_tov_pct":"0.068","four_opp_oreb_pct":"0.278"},{"id":53330,"game_id":21500041,"team_id":1610612745,"opponent_id":1610612748,"player_id":1626149,"box_minutes":1336,"box_fgm":3,"box_fga":4,"box_fg3m":0,"box_fg3a":0,"box_ftm":1,"box_fta":2,"box_oreb":2,"box_dreb":3,"box_ast":0,"box_stl":0,"box_blk":1,"box_to":1,"box_pf":2,"box_pts":7,"box_plus_minus":-18,"trk_speed":"4.32","trk_dist":"1.60","trk_orbc":4,"trk_drbc":4,"trk_touches":23,"trk_sast":0,"trk_ftast":0,"trk_pass":17,"trk_cfgm":2,"trk_cfga":3,"trk_ufgm":1,"trk_ufga":1,"trk_dfgm":3,"trk_dfga":4,"adv_off_rating":"75.2","adv_def_rating":"118.4","adv_ast_pct":"0.000","adv_ast_tov":"0.000","adv_ast_ratio":"0.00","adv_oreb_pct":"0.095","adv_dreb_pct":"0.143","adv_treb_pct":"0.119","adv_tm_tov_pct":"17.0","adv_efg_pct":"0.750","adv_ts_pct":"0.717","adv_usg_pct":"0.112","adv_pace":"105.41","adv_pie":"0.079","misc_pts_off_tov":0,"misc_pts_2nd_chance":4,"misc_pts_fb":0,"misc_pts_paint":6,"misc_opp_pts_off_tov":10,"misc_opp_pts_2nd_chance":13,"misc_opp_pts_fb":8,"misc_opp_pts_paint":32,"misc_blk":1,"misc_blka":0,"misc_pf":2,"misc_pfd":2,"scr_pct_2pt_fga":"1.000","scr_pct_pts_2pt":"0.857","scr_pct_pts_2ptmr":"0.000","scr_pct_pts_3pt":"0.000","scr_pct_pts_fb":"0.000","scr_pct_pts_ft":"0.143","scr_pct_pts_off_tov":"0.000","scr_pct_pts_paint":"0.857","scr_pct_pts_ast_2pm":"0.667","scr_pct_pts_ast_3pm":"0.000","scr_pct_pts_ast_fgm":"0.667","usg_pct":"0.112","usg_pct_fgm":"0.200","usg_pct_fga":"0.103","usg_pct_fg3m":"0.000","usg_pct_fg3a":"0.000","usg_pct_ftm":"0.143","usg_pct_fta":"0.250","usg_pct_oreb":"1.000","usg_pct_dreb":"0.214","usg_pct_reb":"0.313","usg_pct_ast":"0.000","usg_pct_stl":"0.000","usg_pct_tov":"0.100","usg_pct_blk":"1.000","usg_pct_blka":"0.000","usg_pct_pf":"0.200","usg_pct_pfd":"0.250","usg_pct_pts":"0.184","four_efg_pct":"0.397","four_fta_rate":"0.205","four_tm_tov_pct":"0.198","four_oreb_pct":"0.095","four_opp_efg_pct":"0.547","four_opp_fta_rate":"0.279","four_opp_tm_tov_pct":"0.127","four_opp_oreb_pct":"0.333"},{"id":53524,"game_id":21500049,"team_id":1610612745,"opponent_id":1610612760,"player_id":1626149,"box_minutes":159,"box_fgm":0,"box_fga":0,"box_fg3m":0,"box_fg3a":0,"box_ftm":0,"box_fta":0,"box_oreb":0,"box_dreb":0,"box_ast":0,"box_stl":1,"box_blk":0,"box_to":0,"box_pf":1,"box_pts":0,"box_plus_minus":-4,"trk_speed":"4.52","trk_dist":"0.20","trk_orbc":0,"trk_drbc":0,"trk_touches":2,"trk_sast":0,"trk_ftast":0,"trk_pass":2,"trk_cfgm":0,"trk_cfga":0,"trk_ufgm":0,"trk_ufga":0,"trk_dfgm":1,"trk_dfga":1,"adv_off_rating":"110.8","adv_def_rating":"170.8","adv_ast_pct":"0.000","adv_ast_tov":"0.000","adv_ast_ratio":"0.00","adv_oreb_pct":"0.000","adv_dreb_pct":"0.000","adv_treb_pct":"0.000","adv_tm_tov_pct":"0.0","adv_efg_pct":"0.000","adv_ts_pct":"0.000","adv_usg_pct":"0.000","adv_pace":"115.56","adv_pie":"0.000","misc_pts_off_tov":0,"misc_pts_2nd_chance":0,"misc_pts_fb":0,"misc_pts_paint":0,"misc_opp_pts_off_tov":0,"misc_opp_pts_2nd_chance":2,"misc_opp_pts_fb":2,"misc_opp_pts_paint":6,"misc_blk":0,"misc_blka":0,"misc_pf":1,"misc_pfd":0,"scr_pct_2pt_fga":"0.000","scr_pct_pts_2pt":"0.000","scr_pct_pts_2ptmr":"0.000","scr_pct_pts_3pt":"0.000","scr_pct_pts_fb":"0.000","scr_pct_pts_ft":"0.000","scr_pct_pts_off_tov":"0.000","scr_pct_pts_paint":"0.000","scr_pct_pts_ast_2pm":"0.000","scr_pct_pts_ast_3pm":"0.000","scr_pct_pts_ast_fgm":"0.000","usg_pct":"0.000","usg_pct_fgm":"0.000","usg_pct_fga":"0.000","usg_pct_fg3m":"0.000","usg_pct_fg3a":"0.000","usg_pct_ftm":"0.000","usg_pct_fta":"0.000","usg_pct_oreb":"0.000","usg_pct_dreb":"0.000","usg_pct_reb":"0.000","usg_pct_ast":"0.000","usg_pct_stl":"1.000","usg_pct_tov":"0.000","usg_pct_blk":"0.000","usg_pct_blka":"0.000","usg_pct_pf":"1.000","usg_pct_pfd":"0.000","usg_pct_pts":"0.000","four_efg_pct":"0.400","four_fta_rate":"0.600","four_tm_tov_pct":"0.000","four_oreb_pct":"0.000","four_opp_efg_pct":"0.917","four_opp_fta_rate":"0.167","four_opp_tm_tov_pct":"0.155","four_opp_oreb_pct":"0.500"},{"id":53853,"game_id":21500064,"team_id":1610612745,"opponent_id":1610612753,"player_id":1626149,"box_minutes":178,"box_fgm":0,"box_fga":0,"box_fg3m":0,"box_fg3a":0,"box_ftm":0,"box_fta":0,"box_oreb":0,"box_dreb":0,"box_ast":0,"box_stl":0,"box_blk":0,"box_to":0,"box_pf":0,"box_pts":0,"box_plus_minus":-6,"trk_speed":"4.56","trk_dist":"0.23","trk_orbc":1,"trk_drbc":0,"trk_touches":2,"trk_sast":1,"trk_ftast":0,"trk_pass":2,"trk_cfgm":0,"trk_cfga":0,"trk_ufgm":0,"trk_ufga":0,"trk_dfgm":1,"trk_dfga":1,"adv_off_rating":"118.3","adv_def_rating":"221.5","adv_ast_pct":"0.000","adv_ast_tov":"0.000","adv_ast_ratio":"0.00","adv_oreb_pct":"0.000","adv_dreb_pct":"0.000","adv_treb_pct":"0.000","adv_tm_tov_pct":"0.0","adv_efg_pct":"0.000","adv_ts_pct":"0.000","adv_usg_pct":"0.000","adv_pace":"105.82","adv_pie":"0.000","misc_pts_off_tov":0,"misc_pts_2nd_chance":0,"misc_pts_fb":0,"misc_pts_paint":0,"misc_opp_pts_off_tov":2,"misc_opp_pts_2nd_chance":0,"misc_opp_pts_fb":4,"misc_opp_pts_paint":6,"misc_blk":0,"misc_blka":0,"misc_pf":0,"misc_pfd":0,"scr_pct_2pt_fga":"0.000","scr_pct_pts_2pt":"0.000","scr_pct_pts_2ptmr":"0.000","scr_pct_pts_3pt":"0.000","scr_pct_pts_fb":"0.000","scr_pct_pts_ft":"0.000","scr_pct_pts_off_tov":"0.000","scr_pct_pts_paint":"0.000","scr_pct_pts_ast_2pm":"0.000","scr_pct_pts_ast_3pm":"0.000","scr_pct_pts_ast_fgm":"0.000","usg_pct":"0.000","usg_pct_fgm":"0.000","usg_pct_fga":"0.000","usg_pct_fg3m":"0.000","usg_pct_fg3a":"0.000","usg_pct_ftm":"0.000","usg_pct_fta":"0.000","usg_pct_oreb":"0.000","usg_pct_dreb":"0.000","usg_pct_reb":"0.000","usg_pct_ast":"0.000","usg_pct_stl":"0.000","usg_pct_tov":"0.000","usg_pct_blk":"0.000","usg_pct_blka":"0.000","usg_pct_pf":"0.000","usg_pct_pfd":"0.000","usg_pct_pts":"0.000","four_efg_pct":"0.625","four_fta_rate":"1.000","four_tm_tov_pct":"0.148","four_oreb_pct":"0.000","four_opp_efg_pct":"1.100","four_opp_fta_rate":"0.600","four_opp_tm_tov_pct":"0.000","four_opp_oreb_pct":"0.000"},{"id":54287,"game_id":21500084,"team_id":1610612745,"opponent_id":1610612758,"player_id":1626149,"box_minutes":396,"box_fgm":1,"box_fga":4,"box_fg3m":0,"box_fg3a":0,"box_ftm":1,"box_fta":2,"box_oreb":2,"box_dreb":0,"box_ast":0,"box_stl":0,"box_blk":0,"box_to":2,"box_pf":1,"box_pts":3,"box_plus_minus":-10,"trk_speed":"4.70","trk_dist":"0.52","trk_orbc":3,"trk_drbc":0,"trk_touches":13,"trk_sast":0,"trk_ftast":0,"trk_pass":7,"trk_cfgm":0,"trk_cfga":3,"trk_ufgm":1,"trk_ufga":1,"trk_dfgm":2,"trk_dfga":2,"adv_off_rating":"88.1","adv_def_rating":"134.7","adv_ast_pct":"0.000","adv_ast_tov":"0.000","adv_ast_ratio":"0.00","adv_oreb_pct":"0.250","adv_dreb_pct":"0.000","adv_treb_pct":"0.167","adv_tm_tov_pct":"29.1","adv_efg_pct":"0.250","adv_ts_pct":"0.307","adv_usg_pct":"0.348","adv_pace":"115.81","adv_pie":"-0.098","misc_pts_off_tov":0,"misc_pts_2nd_chance":0,"misc_pts_fb":1,"misc_pts_paint":2,"misc_opp_pts_off_tov":10,"misc_opp_pts_2nd_chance":0,"misc_opp_pts_fb":9,"misc_opp_pts_paint":12,"misc_blk":0,"misc_blka":2,"misc_pf":1,"misc_pfd":1,"scr_pct_2pt_fga":"1.000","scr_pct_pts_2pt":"0.667","scr_pct_pts_2ptmr":"0.000","scr_pct_pts_3pt":"0.000","scr_pct_pts_fb":"0.333","scr_pct_pts_ft":"0.333","scr_pct_pts_off_tov":"0.000","scr_pct_pts_paint":"0.667","scr_pct_pts_ast_2pm":"1.000","scr_pct_pts_ast_3pm":"0.000","scr_pct_pts_ast_fgm":"1.000","usg_pct":"0.348","usg_pct_fgm":"0.250","usg_pct_fga":"0.333","usg_pct_fg3m":"0.000","usg_pct_fg3a":"0.000","usg_pct_ftm":"0.333","usg_pct_fta":"0.500","usg_pct_oreb":"0.400","usg_pct_dreb":"0.000","usg_pct_reb":"0.222","usg_pct_ast":"0.000","usg_pct_stl":"0.000","usg_pct_tov":"0.333","usg_pct_blk":"0.000","usg_pct_blka":"1.000","usg_pct_pf":"0.250","usg_pct_pfd":"0.500","usg_pct_pts":"0.231","four_efg_pct":"0.417","four_fta_rate":"0.333","four_tm_tov_pct":"0.407","four_oreb_pct":"0.625","four_opp_efg_pct":"0.818","four_opp_fta_rate":"0.636","four_opp_tm_tov_pct":"0.176","four_opp_oreb_pct":"0.000"},{"id":54481,"game_id":21500093,"team_id":1610612745,"opponent_id":1610612746,"player_id":1626149,"box_minutes":250,"box_fgm":0,"box_fga":0,"box_fg3m":0,"box_fg3a":0,"box_ftm":0,"box_fta":0,"box_oreb":0,"box_dreb":1,"box_ast":0,"box_stl":0,"box_blk":0,"box_to":0,"box_pf":0,"box_pts":0,"box_plus_minus":1,"trk_speed":"4.19","trk_dist":"0.29","trk_orbc":1,"trk_drbc":1,"trk_touches":3,"trk_sast":0,"trk_ftast":0,"trk_pass":3,"trk_cfgm":0,"trk_cfga":0,"trk_ufgm":0,"trk_ufga":0,"trk_dfgm":1,"trk_dfga":1,"adv_off_rating":"139.5","adv_def_rating":"127.1","adv_ast_pct":"0.000","adv_ast_tov":"0.000","adv_ast_ratio":"0.00","adv_oreb_pct":"0.000","adv_dreb_pct":"0.250","adv_treb_pct":"0.125","adv_tm_tov_pct":"0.0","adv_efg_pct":"0.000","adv_ts_pct":"0.000","adv_usg_pct":"0.000","adv_pace":"108.06","adv_pie":"0.039","misc_pts_off_tov":0,"misc_pts_2nd_chance":0,"misc_pts_fb":0,"misc_pts_paint":0,"misc_opp_pts_off_tov":0,"misc_opp_pts_2nd_chance":0,"misc_opp_pts_fb":5,"misc_opp_pts_paint":4,"misc_blk":0,"misc_blka":0,"misc_pf":0,"misc_pfd":0,"scr_pct_2pt_fga":"0.000","scr_pct_pts_2pt":"0.000","scr_pct_pts_2ptmr":"0.000","scr_pct_pts_3pt":"0.000","scr_pct_pts_fb":"0.000","scr_pct_pts_ft":"0.000","scr_pct_pts_off_tov":"0.000","scr_pct_pts_paint":"0.000","scr_pct_pts_ast_2pm":"0.000","scr_pct_pts_ast_3pm":"0.000","scr_pct_pts_ast_fgm":"0.000","usg_pct":"0.000","usg_pct_fgm":"0.000","usg_pct_fga":"0.000","usg_pct_fg3m":"0.000","usg_pct_fg3a":"0.000","usg_pct_ftm":"0.000","usg_pct_fta":"0.000","usg_pct_oreb":"0.000","usg_pct_dreb":"0.250","usg_pct_reb":"0.200","usg_pct_ast":"0.000","usg_pct_stl":"0.000","usg_pct_tov":"0.000","usg_pct_blk":"0.000","usg_pct_blka":"0.000","usg_pct_pf":"0.000","usg_pct_pfd":"0.000","usg_pct_pts":"0.000","four_efg_pct":"0.556","four_fta_rate":"0.333","four_tm_tov_pct":"0.000","four_oreb_pct":"0.250","four_opp_efg_pct":"0.611","four_opp_fta_rate":"0.111","four_opp_tm_tov_pct":"0.000","four_opp_oreb_pct":"0.000"},{"id":55257,"game_id":21500136,"team_id":1610612745,"opponent_id":1610612743,"player_id":1626149,"box_minutes":771,"box_fgm":1,"box_fga":1,"box_fg3m":0,"box_fg3a":0,"box_ftm":3,"box_fta":4,"box_oreb":1,"box_dreb":1,"box_ast":0,"box_stl":0,"box_blk":0,"box_to":1,"box_pf":3,"box_pts":5,"box_plus_minus":-1,"trk_speed":"4.48","trk_dist":"0.96","trk_orbc":2,"trk_drbc":1,"trk_touches":14,"trk_sast":0,"trk_ftast":0,"trk_pass":10,"trk_cfgm":1,"trk_cfga":1,"trk_ufgm":0,"trk_ufga":0,"trk_dfgm":1,"trk_dfga":2,"adv_off_rating":"104.9","adv_def_rating":"107.0","adv_ast_pct":"0.000","adv_ast_tov":"0.000","adv_ast_ratio":"0.00","adv_oreb_pct":"0.091","adv_dreb_pct":"0.083","adv_treb_pct":"0.087","adv_tm_tov_pct":"26.6","adv_efg_pct":"1.000","adv_ts_pct":"0.906","adv_usg_pct":"0.115","adv_pace":"107.51","adv_pie":"0.030","misc_pts_off_tov":2,"misc_pts_2nd_chance":2,"misc_pts_fb":2,"misc_pts_paint":2,"misc_opp_pts_off_tov":11,"misc_opp_pts_2nd_chance":4,"misc_opp_pts_fb":10,"misc_opp_pts_paint":16,"misc_blk":0,"misc_blka":0,"misc_pf":3,"misc_pfd":2,"scr_pct_2pt_fga":"1.000","scr_pct_pts_2pt":"0.400","scr_pct_pts_2ptmr":"0.000","scr_pct_pts_3pt":"0.000","scr_pct_pts_fb":"0.400","scr_pct_pts_ft":"0.600","scr_pct_pts_off_tov":"0.400","scr_pct_pts_paint":"0.400","scr_pct_pts_ast_2pm":"0.000","scr_pct_pts_ast_3pm":"0.000","scr_pct_pts_ast_fgm":"0.000","usg_pct":"0.115","usg_pct_fgm":"0.143","usg_pct_fga":"0.053","usg_pct_fg3m":"0.000","usg_pct_fg3a":"0.000","usg_pct_ftm":"0.214","usg_pct_fta":"0.267","usg_pct_oreb":"0.250","usg_pct_dreb":"0.111","usg_pct_reb":"0.154","usg_pct_ast":"0.000","usg_pct_stl":"0.000","usg_pct_tov":"0.143","usg_pct_blk":"0.000","usg_pct_blka":"0.000","usg_pct_pf":"0.500","usg_pct_pfd":"0.250","usg_pct_pts":"0.167","four_efg_pct":"0.421","four_fta_rate":"0.789","four_tm_tov_pct":"0.245","four_oreb_pct":"0.364","four_opp_efg_pct":"0.500","four_opp_fta_rate":"0.375","four_opp_tm_tov_pct":"0.138","four_opp_oreb_pct":"0.250"},{"id":55356,"game_id":21500140,"team_id":1610612745,"opponent_id":1610612742,"player_id":1626149,"box_minutes":663,"box_fgm":2,"box_fga":3,"box_fg3m":0,"box_fg3a":0,"box_ftm":1,"box_fta":2,"box_oreb":2,"box_dreb":2,"box_ast":1,"box_stl":1,"box_blk":1,"box_to":0,"box_pf":1,"box_pts":5,"box_plus_minus":3,"trk_speed":"3.93","trk_dist":"0.73","trk_orbc":4,"trk_drbc":3,"trk_touches":18,"trk_sast":0,"trk_ftast":0,"trk_pass":14,"trk_cfgm":2,"trk_cfga":3,"trk_ufgm":0,"trk_ufga":0,"trk_dfgm":2,"trk_dfga":2,"adv_off_rating":"118.4","adv_def_rating":"105.7","adv_ast_pct":"0.143","adv_ast_tov":"0.000","adv_ast_ratio":"20.50","adv_oreb_pct":"0.222","adv_dreb_pct":"0.200","adv_treb_pct":"0.211","adv_tm_tov_pct":"0.0","adv_efg_pct":"0.667","adv_ts_pct":"0.644","adv_usg_pct":"0.144","adv_pace":"94.96","adv_pie":"0.197","misc_pts_off_tov":0,"misc_pts_2nd_chance":1,"misc_pts_fb":0,"misc_pts_paint":4,"misc_opp_pts_off_tov":5,"misc_opp_pts_2nd_chance":6,"misc_opp_pts_fb":3,"misc_opp_pts_paint":16,"misc_blk":1,"misc_blka":1,"misc_pf":1,"misc_pfd":1,"scr_pct_2pt_fga":"1.000","scr_pct_pts_2pt":"0.800","scr_pct_pts_2ptmr":"0.000","scr_pct_pts_3pt":"0.000","scr_pct_pts_fb":"0.000","scr_pct_pts_ft":"0.200","scr_pct_pts_off_tov":"0.000","scr_pct_pts_paint":"0.800","scr_pct_pts_ast_2pm":"0.500","scr_pct_pts_ast_3pm":"0.000","scr_pct_pts_ast_fgm":"0.500","usg_pct":"0.144","usg_pct_fgm":"0.222","usg_pct_fga":"0.150","usg_pct_fg3m":"0.000","usg_pct_fg3a":"0.000","usg_pct_ftm":"0.167","usg_pct_fta":"0.222","usg_pct_oreb":"0.400","usg_pct_dreb":"0.286","usg_pct_reb":"0.333","usg_pct_ast":"0.167","usg_pct_stl":"1.000","usg_pct_tov":"0.000","usg_pct_blk":"1.000","usg_pct_blka":"1.000","usg_pct_pf":"0.200","usg_pct_pfd":"0.200","usg_pct_pts":"0.192","four_efg_pct":"0.500","four_fta_rate":"0.450","four_tm_tov_pct":"0.137","four_oreb_pct":"0.556","four_opp_efg_pct":"0.452","four_opp_fta_rate":"0.190","four_opp_tm_tov_pct":"0.092","four_opp_oreb_pct":"0.300"},{"id":55652,"game_id":21500154,"team_id":1610612745,"opponent_id":1610612738,"player_id":1626149,"box_minutes":717,"box_fgm":2,"box_fga":3,"box_fg3m":0,"box_fg3a":0,"box_ftm":0,"box_fta":0,"box_oreb":0,"box_dreb":2,"box_ast":0,"box_stl":0,"box_blk":0,"box_to":2,"box_pf":1,"box_pts":4,"box_plus_minus":0,"trk_speed":"4.24","trk_dist":"0.85","trk_orbc":0,"trk_drbc":2,"trk_touches":17,"trk_sast":0,"trk_ftast":0,"trk_pass":11,"trk_cfgm":1,"trk_cfga":2,"trk_ufgm":1,"trk_ufga":1,"trk_dfgm":0,"trk_dfga":1,"adv_off_rating":"97.7","adv_def_rating":"97.3","adv_ast_pct":"0.000","adv_ast_tov":"0.000","adv_ast_ratio":"0.00","adv_oreb_pct":"0.000","adv_dreb_pct":"0.154","adv_treb_pct":"0.095","adv_tm_tov_pct":"40.0","adv_efg_pct":"0.667","adv_ts_pct":"0.667","adv_usg_pct":"0.163","adv_pace":"111.34","adv_pie":"0.053","misc_pts_off_tov":0,"misc_pts_2nd_chance":0,"misc_pts_fb":0,"misc_pts_paint":2,"misc_opp_pts_off_tov":15,"misc_opp_pts_2nd_chance":4,"misc_opp_pts_fb":7,"misc_opp_pts_paint":10,"misc_blk":0,"misc_blka":0,"misc_pf":1,"misc_pfd":1,"scr_pct_2pt_fga":"1.000","scr_pct_pts_2pt":"1.000","scr_pct_pts_2ptmr":"0.500","scr_pct_pts_3pt":"0.000","scr_pct_pts_fb":"0.000","scr_pct_pts_ft":"0.000","scr_pct_pts_off_tov":"0.000","scr_pct_pts_paint":"0.500","scr_pct_pts_ast_2pm":"1.000","scr_pct_pts_ast_3pm":"0.000","scr_pct_pts_ast_fgm":"1.000","usg_pct":"0.163","usg_pct_fgm":"0.200","usg_pct_fga":"0.158","usg_pct_fg3m":"0.000","usg_pct_fg3a":"0.000","usg_pct_ftm":"0.000","usg_pct_fta":"0.000","usg_pct_oreb":"0.000","usg_pct_dreb":"0.222","usg_pct_reb":"0.167","usg_pct_ast":"0.000","usg_pct_stl":"0.000","usg_pct_tov":"0.222","usg_pct_blk":"0.000","usg_pct_blka":"0.000","usg_pct_pf":"0.167","usg_pct_pfd":"0.167","usg_pct_pts":"0.148","four_efg_pct":"0.605","four_fta_rate":"0.316","four_tm_tov_pct":"0.326","four_oreb_pct":"0.375","four_opp_efg_pct":"0.522","four_opp_fta_rate":"0.174","four_opp_tm_tov_pct":"0.252","four_opp_oreb_pct":"0.308"},{"id":55989,"game_id":21500170,"team_id":1610612745,"opponent_id":1610612757,"player_id":1626149,"box_minutes":388,"box_fgm":0,"box_fga":0,"box_fg3m":0,"box_fg3a":0,"box_ftm":0,"box_fta":0,"box_oreb":0,"box_dreb":0,"box_ast":0,"box_stl":1,"box_blk":0,"box_to":0,"box_pf":1,"box_pts":0,"box_plus_minus":-3,"trk_speed":"4.36","trk_dist":"0.47","trk_orbc":1,"trk_drbc":2,"trk_touches":6,"trk_sast":0,"trk_ftast":0,"trk_pass":6,"trk_cfgm":0,"trk_cfga":0,"trk_ufgm":0,"trk_ufga":0,"trk_dfgm":0,"trk_dfga":0,"adv_off_rating":"33.3","adv_def_rating":"50.4","adv_ast_pct":"0.000","adv_ast_tov":"0.000","adv_ast_ratio":"0.00","adv_oreb_pct":"0.000","adv_dreb_pct":"0.000","adv_treb_pct":"0.000","adv_tm_tov_pct":"0.0","adv_efg_pct":"0.000","adv_ts_pct":"0.000","adv_usg_pct":"0.000","adv_pace":"96.12","adv_pie":"0.000","misc_pts_off_tov":0,"misc_pts_2nd_chance":0,"misc_pts_fb":0,"misc_pts_paint":0,"misc_opp_pts_off_tov":0,"misc_opp_pts_2nd_chance":1,"misc_opp_pts_fb":0,"misc_opp_pts_paint":0,"misc_blk":0,"misc_blka":0,"misc_pf":1,"misc_pfd":1,"scr_pct_2pt_fga":"0.000","scr_pct_pts_2pt":"0.000","scr_pct_pts_2ptmr":"0.000","scr_pct_pts_3pt":"0.000","scr_pct_pts_fb":"0.000","scr_pct_pts_ft":"0.000","scr_pct_pts_off_tov":"0.000","scr_pct_pts_paint":"0.000","scr_pct_pts_ast_2pm":"0.000","scr_pct_pts_ast_3pm":"0.000","scr_pct_pts_ast_fgm":"0.000","usg_pct":"0.000","usg_pct_fgm":"0.000","usg_pct_fga":"0.000","usg_pct_fg3m":"0.000","usg_pct_fg3a":"0.000","usg_pct_ftm":"0.000","usg_pct_fta":"0.000","usg_pct_oreb":"0.000","usg_pct_dreb":"0.000","usg_pct_reb":"0.000","usg_pct_ast":"0.000","usg_pct_stl":"0.500","usg_pct_tov":"0.000","usg_pct_blk":"0.000","usg_pct_blka":"0.000","usg_pct_pf":"0.500","usg_pct_pfd":"0.333","usg_pct_pts":"0.000","four_efg_pct":"0.182","four_fta_rate":"0.000","four_tm_tov_pct":"0.167","four_oreb_pct":"0.125","four_opp_efg_pct":"0.273","four_opp_fta_rate":"0.182","four_opp_tm_tov_pct":"0.360","four_opp_oreb_pct":"0.375"},{"id":56189,"game_id":21500180,"team_id":1610612745,"opponent_id":1610612763,"player_id":1626149,"box_minutes":306,"box_fgm":0,"box_fga":0,"box_fg3m":0,"box_fg3a":0,"box_ftm":0,"box_fta":2,"box_oreb":0,"box_dreb":1,"box_ast":0,"box_stl":0,"box_blk":0,"box_to":2,"box_pf":1,"box_pts":0,"box_plus_minus":-2,"trk_speed":"4.32","trk_dist":"0.37","trk_orbc":1,"trk_drbc":2,"trk_touches":7,"trk_sast":0,"trk_ftast":0,"trk_pass":5,"trk_cfgm":0,"trk_cfga":0,"trk_ufgm":0,"trk_ufga":0,"trk_dfgm":0,"trk_dfga":1,"adv_off_rating":"48.4","adv_def_rating":"73.5","adv_ast_pct":"0.000","adv_ast_tov":"0.000","adv_ast_ratio":"0.00","adv_oreb_pct":"0.000","adv_dreb_pct":"0.143","adv_treb_pct":"0.071","adv_tm_tov_pct":"69.4","adv_efg_pct":"0.000","adv_ts_pct":"0.000","adv_usg_pct":"0.232","adv_pace":"109.70","adv_pie":"-0.889","misc_pts_off_tov":0,"misc_pts_2nd_chance":0,"misc_pts_fb":0,"misc_pts_paint":0,"misc_opp_pts_off_tov":5,"misc_opp_pts_2nd_chance":0,"misc_opp_pts_fb":2,"misc_opp_pts_paint":4,"misc_blk":0,"misc_blka":0,"misc_pf":1,"misc_pfd":1,"scr_pct_2pt_fga":"0.000","scr_pct_pts_2pt":"0.000","scr_pct_pts_2ptmr":"0.000","scr_pct_pts_3pt":"0.000","scr_pct_pts_fb":"0.000","scr_pct_pts_ft":"0.000","scr_pct_pts_off_tov":"0.000","scr_pct_pts_paint":"0.000","scr_pct_pts_ast_2pm":"0.000","scr_pct_pts_ast_3pm":"0.000","scr_pct_pts_ast_fgm":"0.000","usg_pct":"0.232","usg_pct_fgm":"0.000","usg_pct_fga":"0.000","usg_pct_fg3m":"0.000","usg_pct_fg3a":"0.000","usg_pct_ftm":"0.000","usg_pct_fta":"0.200","usg_pct_oreb":"0.000","usg_pct_dreb":"0.200","usg_pct_reb":"0.200","usg_pct_ast":"0.000","usg_pct_stl":"0.000","usg_pct_tov":"1.000","usg_pct_blk":"0.000","usg_pct_blka":"0.000","usg_pct_pf":"0.500","usg_pct_pfd":"0.200","usg_pct_pts":"0.000","four_efg_pct":"0.000","four_fta_rate":"1.667","four_tm_tov_pct":"0.161","four_oreb_pct":"0.000","four_opp_efg_pct":"0.389","four_opp_fta_rate":"0.222","four_opp_tm_tov_pct":"0.276","four_opp_oreb_pct":"0.286"},{"id":56498,"game_id":21500194,"team_id":1610612745,"opponent_id":1610612752,"player_id":1626149,"box_minutes":660,"box_fgm":1,"box_fga":2,"box_fg3m":0,"box_fg3a":0,"box_ftm":1,"box_fta":2,"box_oreb":1,"box_dreb":0,"box_ast":0,"box_stl":0,"box_blk":2,"box_to":0,"box_pf":2,"box_pts":3,"box_plus_minus":-14,"trk_speed":"4.12","trk_dist":"0.76","trk_orbc":2,"trk_drbc":1,"trk_touches":11,"trk_sast":1,"trk_ftast":0,"trk_pass":8,"trk_cfgm":1,"trk_cfga":1,"trk_ufgm":0,"trk_ufga":1,"trk_dfgm":1,"trk_dfga":3,"adv_off_rating":"110.8","adv_def_rating":"147.6","adv_ast_pct":"0.000","adv_ast_tov":"0.000","adv_ast_ratio":"0.00","adv_oreb_pct":"0.091","adv_dreb_pct":"0.000","adv_treb_pct":"0.048","adv_tm_tov_pct":"0.0","adv_efg_pct":"0.500","adv_ts_pct":"0.521","adv_usg_pct":"0.120","adv_pace":"93.19","adv_pie":"0.013","misc_pts_off_tov":1,"misc_pts_2nd_chance":0,"misc_pts_fb":0,"misc_pts_paint":2,"misc_opp_pts_off_tov":3,"misc_opp_pts_2nd_chance":3,"misc_opp_pts_fb":2,"misc_opp_pts_paint":4,"misc_blk":2,"misc_blka":0,"misc_pf":2,"misc_pfd":1,"scr_pct_2pt_fga":"1.000","scr_pct_pts_2pt":"0.667","scr_pct_pts_2ptmr":"0.000","scr_pct_pts_3pt":"0.000","scr_pct_pts_fb":"0.000","scr_pct_pts_ft":"0.333","scr_pct_pts_off_tov":"0.333","scr_pct_pts_paint":"0.667","scr_pct_pts_ast_2pm":"1.000","scr_pct_pts_ast_3pm":"0.000","scr_pct_pts_ast_fgm":"1.000","usg_pct":"0.120","usg_pct_fgm":"0.143","usg_pct_fga":"0.118","usg_pct_fg3m":"0.000","usg_pct_fg3a":"0.000","usg_pct_ftm":"0.167","usg_pct_fta":"0.222","usg_pct_oreb":"0.200","usg_pct_dreb":"0.000","usg_pct_reb":"0.091","usg_pct_ast":"0.000","usg_pct_stl":"0.000","usg_pct_tov":"0.000","usg_pct_blk":"1.000","usg_pct_blka":"0.000","usg_pct_pf":"0.250","usg_pct_pfd":"0.143","usg_pct_pts":"0.143","four_efg_pct":"0.441","four_fta_rate":"0.529","four_tm_tov_pct":"0.158","four_oreb_pct":"0.455","four_opp_efg_pct":"0.625","four_opp_fta_rate":"0.650","four_opp_tm_tov_pct":"0.084","four_opp_oreb_pct":"0.400"}]