[{"id":551,"game_id":21300027,"team_id":1610612760,"opponent_id":1610612750,"player_id":101155,"box_minutes":376,"box_fgm":0,"box_fga":1,"box_fg3m":0,"box_fg3a":0,"box_ftm":0,"box_fta":0,"box_oreb":0,"box_dreb":1,"box_ast":1,"box_stl":0,"box_blk":0,"box_to":0,"box_pf":0,"box_pts":0,"box_plus_minus":12,"trk_speed":"3.87","trk_dist":"0.41","trk_orbc":0,"trk_drbc":1,"trk_touches":9,"trk_sast":0,"trk_ftast":0,"trk_pass":8,"trk_cfgm":0,"trk_cfga":1,"trk_ufgm":0,"trk_ufga":0,"trk_dfgm":0,"trk_dfga":0,"adv_off_rating":"111.5","adv_def_rating":"0.0","adv_ast_pct":"0.250","adv_ast_tov":"0.000","adv_ast_ratio":"50.00","adv_oreb_pct":"0.000","adv_dreb_pct":"0.333","adv_treb_pct":"0.083","adv_tm_tov_pct":"0.0","adv_efg_pct":"0.000","adv_ts_pct":"0.000","adv_usg_pct":"0.063","adv_pace":"82.88","adv_pie":"-0.250","misc_pts_off_tov":0,"misc_pts_2nd_chance":0,"misc_pts_fb":0,"misc_pts_paint":0,"misc_opp_pts_off_tov":0,"misc_opp_pts_2nd_chance":0,"misc_opp_pts_fb":0,"misc_opp_pts_paint":0,"misc_blk":0,"misc_blka":0,"misc_pf":0,"misc_pfd":0,"scr_pct_2pt_fga":"1.000","scr_pct_pts_2pt":"0.000","scr_pct_pts_2ptmr":"0.000","scr_pct_pts_3pt":"0.000","scr_pct_pts_fb":"0.000","scr_pct_pts_ft":"0.000","scr_pct_pts_off_tov":"0.000","scr_pct_pts_paint":"0.000","scr_pct_pts_ast_2pm":"0.000","scr_pct_pts_ast_3pm":"0.000","scr_pct_pts_ast_fgm":"0.000","usg_pct":"0.063","usg_pct_fgm":"0.000","usg_pct_fga":"0.077","usg_pct_fg3m":"0.000","usg_pct_fg3a":"0.000","usg_pct_ftm":"0.000","usg_pct_fta":"0.000","usg_pct_oreb":"0.000","usg_pct_dreb":"0.333","usg_pct_reb":"0.125","usg_pct_ast":"0.500","usg_pct_stl":"0.000","usg_pct_tov":"0.000","usg_pct_blk":"0.000","usg_pct_blka":"0.000","usg_pct_pf":"0.000","usg_pct_pfd":"0.000","usg_pct_pts":"0.000","four_efg_pct":"0.346","four_fta_rate":"0.308","four_tm_tov_pct":"0.093","four_oreb_pct":"0.556","four_opp_efg_pct":"0.000","four_opp_fta_rate":"0.400","four_opp_tm_tov_pct":"0.460","four_opp_oreb_pct":"0.000"},{"id":2585,"game_id":21300122,"team_id":1610612760,"opponent_id":1610612746,"player_id":101155,"box_minutes":358,"box_fgm":1,"box_fga":1,"box_fg3m":0,"box_fg3a":0,"box_ftm":0,"box_fta":0,"box_oreb":0,"box_dreb":0,"box_ast":0,"box_stl":0,"box_blk":0,"box_to":1,"box_pf":4,"box_pts":2,"box_plus_minus":-5,"trk_speed":"4.71","trk_dist":"0.47","trk_orbc":0,"trk_drbc":1,"trk_touches":10,"trk_sast":0,"trk_ftast":0,"trk_pass":8,"trk_cfgm":0,"trk_cfga":0,"trk_ufgm":1,"trk_ufga":1,"trk_dfgm":0,"trk_dfga":0,"adv_off_rating":"50.4","adv_def_rating":"94.0","adv_ast_pct":"0.000","adv_ast_tov":"0.000","adv_ast_ratio":"0.00","adv_oreb_pct":"0.000","adv_dreb_pct":"0.000","adv_treb_pct":"0.000","adv_tm_tov_pct":"50.0","adv_efg_pct":"1.000","adv_ts_pct":"1.000","adv_usg_pct":"0.144","adv_pace":"107.16","adv_pie":"-0.250","misc_pts_off_tov":0,"misc_pts_2nd_chance":0,"misc_pts_fb":0,"misc_pts_paint":0,"misc_opp_pts_off_tov":3,"misc_opp_pts_2nd_chance":1,"misc_opp_pts_fb":5,"misc_opp_pts_paint":4,"misc_blk":0,"misc_blka":0,"misc_pf":4,"misc_pfd":0,"scr_pct_2pt_fga":"1.000","scr_pct_pts_2pt":"1.000","scr_pct_pts_2ptmr":"1.000","scr_pct_pts_3pt":"0.000","scr_pct_pts_fb":"0.000","scr_pct_pts_ft":"0.000","scr_pct_pts_off_tov":"0.000","scr_pct_pts_paint":"0.000","scr_pct_pts_ast_2pm":"1.000","scr_pct_pts_ast_3pm":"0.000","scr_pct_pts_ast_fgm":"1.000","usg_pct":"0.144","usg_pct_fgm":"0.333","usg_pct_fga":"0.111","usg_pct_fg3m":"0.000","usg_pct_fg3a":"0.000","usg_pct_ftm":"0.000","usg_pct_fta":"0.000","usg_pct_oreb":"0.000","usg_pct_dreb":"0.000","usg_pct_reb":"0.000","usg_pct_ast":"0.000","usg_pct_stl":"0.000","usg_pct_tov":"0.250","usg_pct_blk":"0.000","usg_pct_blka":"0.000","usg_pct_pf":"0.800","usg_pct_pfd":"0.000","usg_pct_pts":"0.286","four_efg_pct":"0.333","four_fta_rate":"0.222","four_tm_tov_pct":"0.288","four_oreb_pct":"0.000","four_opp_efg_pct":"0.563","four_opp_fta_rate":"0.500","four_opp_tm_tov_pct":"0.392","four_opp_oreb_pct":"0.400"},{"id":4236,"game_id":21300200,"team_id":1610612760,"opponent_id":1610612762,"player_id":101155,"box_minutes":621,"box_fgm":1,"box_fga":4,"box_fg3m":0,"box_fg3a":2,"box_ftm":0,"box_fta":0,"box_oreb":0,"box_dreb":1,"box_ast":0,"box_stl":0,"box_blk":0,"box_to":0,"box_pf":1,"box_pts":2,"box_plus_minus":-7,"trk_speed":"3.89","trk_dist":"0.68","trk_orbc":0,"trk_drbc":2,"trk_touches":11,"trk_sast":0,"trk_ftast":0,"trk_pass":6,"trk_cfgm":1,"trk_cfga":1,"trk_ufgm":0,"trk_ufga":3,"trk_dfgm":0,"trk_dfga":0,"adv_off_rating":"82.6","adv_def_rating":"112.3","adv_ast_pct":"0.000","adv_ast_tov":"0.000","adv_ast_ratio":"0.00","adv_oreb_pct":"0.000","adv_dreb_pct":"0.125","adv_treb_pct":"0.067","adv_tm_tov_pct":"0.0","adv_efg_pct":"0.250","adv_ts_pct":"0.250","adv_usg_pct":"0.159","adv_pace":"111.86","adv_pie":"-0.034","misc_pts_off_tov":0,"misc_pts_2nd_chance":0,"misc_pts_fb":0,"misc_pts_paint":2,"misc_opp_pts_off_tov":8,"misc_opp_pts_2nd_chance":1,"misc_opp_pts_fb":11,"misc_opp_pts_paint":18,"misc_blk":0,"misc_blka":1,"misc_pf":1,"misc_pfd":0,"scr_pct_2pt_fga":"0.500","scr_pct_pts_2pt":"1.000","scr_pct_pts_2ptmr":"0.000","scr_pct_pts_3pt":"0.000","scr_pct_pts_fb":"0.000","scr_pct_pts_ft":"0.000","scr_pct_pts_off_tov":"0.000","scr_pct_pts_paint":"1.000","scr_pct_pts_ast_2pm":"1.000","scr_pct_pts_ast_3pm":"0.000","scr_pct_pts_ast_fgm":"1.000","usg_pct":"0.159","usg_pct_fgm":"0.125","usg_pct_fga":"0.250","usg_pct_fg3m":"0.000","usg_pct_fg3a":"0.500","usg_pct_ftm":"0.000","usg_pct_fta":"0.000","usg_pct_oreb":"0.000","usg_pct_dreb":"0.125","usg_pct_reb":"0.111","usg_pct_ast":"0.000","usg_pct_stl":"0.000","usg_pct_tov":"0.000","usg_pct_blk":"0.000","usg_pct_blka":"0.500","usg_pct_pf":"0.091","usg_pct_pfd":"0.000","usg_pct_pts":"0.100","four_efg_pct":"0.531","four_fta_rate":"0.313","four_tm_tov_pct":"0.289","four_oreb_pct":"0.143","four_opp_efg_pct":"0.714","four_opp_fta_rate":"1.143","four_opp_tm_tov_pct":"0.125","four_opp_oreb_pct":"0.000"},{"id":6040,"game_id":21300286,"team_id":1610612760,"opponent_id":1610612740,"player_id":101155,"box_minutes":324,"box_fgm":0,"box_fga":0,"box_fg3m":0,"box_fg3a":0,"box_ftm":0,"box_fta":0,"box_oreb":0,"box_dreb":1,"box_ast":0,"box_stl":0,"box_blk":0,"box_to":0,"box_pf":0,"box_pts":0,"box_plus_minus":1,"trk_speed":"3.95","trk_dist":"0.36","trk_orbc":0,"trk_drbc":1,"trk_touches":9,"trk_sast":0,"trk_ftast":0,"trk_pass":9,"trk_cfgm":0,"trk_cfga":0,"trk_ufgm":0,"trk_ufga":0,"trk_dfgm":0,"trk_dfga":0,"adv_off_rating":"114.2","adv_def_rating":"88.2","adv_ast_pct":"0.000","adv_ast_tov":"0.000","adv_ast_ratio":"0.00","adv_oreb_pct":"0.000","adv_dreb_pct":"0.143","adv_treb_pct":"0.083","adv_tm_tov_pct":"0.0","adv_efg_pct":"0.000","adv_ts_pct":"0.000","adv_usg_pct":"0.000","adv_pace":"84.27","adv_pie":"0.059","misc_pts_off_tov":0,"misc_pts_2nd_chance":0,"misc_pts_fb":0,"misc_pts_paint":0,"misc_opp_pts_off_tov":0,"misc_opp_pts_2nd_chance":2,"misc_opp_pts_fb":0,"misc_opp_pts_paint":2,"misc_blk":0,"misc_blka":0,"misc_pf":0,"misc_pfd":0,"scr_pct_2pt_fga":"0.000","scr_pct_pts_2pt":"0.000","scr_pct_pts_2ptmr":"0.000","scr_pct_pts_3pt":"0.000","scr_pct_pts_fb":"0.000","scr_pct_pts_ft":"0.000","scr_pct_pts_off_tov":"0.000","scr_pct_pts_paint":"0.000","scr_pct_pts_ast_2pm":"0.000","scr_pct_pts_ast_3pm":"0.000","scr_pct_pts_ast_fgm":"0.000","usg_pct":"0.000","usg_pct_fgm":"0.000","usg_pct_fga":"0.000","usg_pct_fg3m":"0.000","usg_pct_fg3a":"0.000","usg_pct_ftm":"0.000","usg_pct_fta":"0.000","usg_pct_oreb":"0.000","usg_pct_dreb":"0.200","usg_pct_reb":"0.143","usg_pct_ast":"0.000","usg_pct_stl":"0.000","usg_pct_tov":"0.000","usg_pct_blk":"0.000","usg_pct_blka":"0.000","usg_pct_pf":"0.000","usg_pct_pfd":"0.000","usg_pct_pts":"0.000","four_efg_pct":"0.375","four_fta_rate":"0.500","four_tm_tov_pct":"0.114","four_oreb_pct":"0.400","four_opp_efg_pct":"0.222","four_opp_fta_rate":"0.556","four_opp_tm_tov_pct":"0.098","four_opp_oreb_pct":"0.286"},{"id":9498,"game_id":21300450,"team_id":1610612760,"opponent_id":1610612745,"player_id":101155,"box_minutes":376,"box_fgm":1,"box_fga":2,"box_fg3m":0,"box_fg3a":0,"box_ftm":0,"box_fta":0,"box_oreb":0,"box_dreb":1,"box_ast":0,"box_stl":0,"box_blk":0,"box_to":0,"box_pf":0,"box_pts":2,"box_plus_minus":6,"trk_speed":"4.08","trk_dist":"0.43","trk_orbc":0,"trk_drbc":2,"trk_touches":7,"trk_sast":1,"trk_ftast":0,"trk_pass":5,"trk_cfgm":0,"trk_cfga":1,"trk_ufgm":1,"trk_ufga":1,"trk_dfgm":1,"trk_dfga":1,"adv_off_rating":"92.3","adv_def_rating":"47.5","adv_ast_pct":"0.000","adv_ast_tov":"0.000","adv_ast_ratio":"0.00","adv_oreb_pct":"0.000","adv_dreb_pct":"0.143","adv_treb_pct":"0.091","adv_tm_tov_pct":"0.0","adv_efg_pct":"0.500","adv_ts_pct":"0.500","adv_usg_pct":"0.154","adv_pace":"98.20","adv_pie":"0.118","misc_pts_off_tov":0,"misc_pts_2nd_chance":0,"misc_pts_fb":0,"misc_pts_paint":0,"misc_opp_pts_off_tov":1,"misc_opp_pts_2nd_chance":0,"misc_opp_pts_fb":1,"misc_opp_pts_paint":4,"misc_blk":0,"misc_blka":0,"misc_pf":0,"misc_pfd":0,"scr_pct_2pt_fga":"1.000","scr_pct_pts_2pt":"1.000","scr_pct_pts_2ptmr":"1.000","scr_pct_pts_3pt":"0.000","scr_pct_pts_fb":"0.000","scr_pct_pts_ft":"0.000","scr_pct_pts_off_tov":"0.000","scr_pct_pts_paint":"0.000","scr_pct_pts_ast_2pm":"1.000","scr_pct_pts_ast_3pm":"0.000","scr_pct_pts_ast_fgm":"1.000","usg_pct":"0.154","usg_pct_fgm":"0.167","usg_pct_fga":"0.200","usg_pct_fg3m":"0.000","usg_pct_fg3a":"0.000","usg_pct_ftm":"0.000","usg_pct_fta":"0.000","usg_pct_oreb":"0.000","usg_pct_dreb":"0.143","usg_pct_reb":"0.143","usg_pct_ast":"0.000","usg_pct_stl":"0.000","usg_pct_tov":"0.000","usg_pct_blk":"0.000","usg_pct_blka":"0.000","usg_pct_pf":"0.000","usg_pct_pfd":"0.000","usg_pct_pts":"0.167","four_efg_pct":"0.600","four_fta_rate":"0.000","four_tm_tov_pct":"0.231","four_oreb_pct":"0.000","four_opp_efg_pct":"0.250","four_opp_fta_rate":"0.750","four_opp_tm_tov_pct":"0.158","four_opp_oreb_pct":"0.000"}]