[{"id":46284,"game_id":21401016,"team_id":1610612750,"opponent_id":1610612752,"player_id":203930,"box_minutes":617,"box_fgm":0,"box_fga":1,"box_fg3m":0,"box_fg3a":1,"box_ftm":0,"box_fta":0,"box_oreb":0,"box_dreb":1,"box_ast":0,"box_stl":0,"box_blk":0,"box_to":1,"box_pf":0,"box_pts":0,"box_plus_minus":5,"trk_speed":"4.36","trk_dist":"0.75","trk_orbc":0,"trk_drbc":1,"trk_touches":6,"trk_sast":0,"trk_ftast":0,"trk_pass":3,"trk_cfgm":0,"trk_cfga":0,"trk_ufgm":0,"trk_ufga":1,"trk_dfgm":0,"trk_dfga":0,"adv_off_rating":"79.7","adv_def_rating":"60.4","adv_ast_pct":"0.000","adv_ast_tov":"0.000","adv_ast_ratio":"0.00","adv_oreb_pct":"0.000","adv_dreb_pct":"0.200","adv_treb_pct":"0.083","adv_tm_tov_pct":"50.0","adv_efg_pct":"0.000","adv_ts_pct":"0.000","adv_usg_pct":"0.094","adv_pace":"96.16","adv_pie":"-0.047","misc_pts_off_tov":0,"misc_pts_2nd_chance":0,"misc_pts_fb":0,"misc_pts_paint":0,"misc_opp_pts_off_tov":4,"misc_opp_pts_2nd_chance":0,"misc_opp_pts_fb":0,"misc_opp_pts_paint":8,"misc_blk":0,"misc_blka":0,"misc_pf":0,"misc_pfd":0,"scr_pct_2pt_fga":"0.000","scr_pct_pts_2pt":"0.000","scr_pct_pts_2ptmr":"0.000","scr_pct_pts_3pt":"0.000","scr_pct_pts_fb":"0.000","scr_pct_pts_ft":"0.000","scr_pct_pts_off_tov":"0.000","scr_pct_pts_paint":"0.000","scr_pct_pts_ast_2pm":"0.000","scr_pct_pts_ast_3pm":"0.000","scr_pct_pts_ast_fgm":"0.000","usg_pct":"0.094","usg_pct_fgm":"0.000","usg_pct_fga":"0.067","usg_pct_fg3m":"0.000","usg_pct_fg3a":"0.333","usg_pct_ftm":"0.000","usg_pct_fta":"0.000","usg_pct_oreb":"0.000","usg_pct_dreb":"0.250","usg_pct_reb":"0.250","usg_pct_ast":"0.000","usg_pct_stl":"0.000","usg_pct_tov":"0.200","usg_pct_blk":"0.000","usg_pct_blka":"0.000","usg_pct_pf":"0.000","usg_pct_pfd":"0.000","usg_pct_pts":"0.000","four_efg_pct":"0.467","four_fta_rate":"0.200","four_tm_tov_pct":"0.235","four_oreb_pct":"0.000","four_opp_efg_pct":"0.385","four_opp_fta_rate":"0.154","four_opp_tm_tov_pct":"0.352","four_opp_oreb_pct":"0.200"},{"id":47508,"game_id":21401052,"team_id":1610612750,"opponent_id":1610612762,"player_id":203930,"box_minutes":1184,"box_fgm":4,"box_fga":7,"box_fg3m":3,"box_fg3a":4,"box_ftm":2,"box_fta":2,"box_oreb":1,"box_dreb":2,"box_ast":2,"box_stl":1,"box_blk":0,"box_to":1,"box_pf":2,"box_pts":13,"box_plus_minus":14,"trk_speed":"4.07","trk_dist":"1.34","trk_orbc":2,"trk_drbc":3,"trk_touches":19,"trk_sast":1,"trk_ftast":0,"trk_pass":11,"trk_cfgm":1,"trk_cfga":3,"trk_ufgm":3,"trk_ufga":4,"trk_dfgm":1,"trk_dfga":1,"adv_off_rating":"114.2","adv_def_rating":"99.2","adv_ast_pct":"0.133","adv_ast_tov":"2.000","adv_ast_ratio":"18.40","adv_oreb_pct":"0.071","adv_dreb_pct":"0.143","adv_treb_pct":"0.107","adv_tm_tov_pct":"9.2","adv_efg_pct":"0.786","adv_ts_pct":"0.825","adv_usg_pct":"0.186","adv_pace":"99.65","adv_pie":"0.160","misc_pts_off_tov":0,"misc_pts_2nd_chance":0,"misc_pts_fb":0,"misc_pts_paint":0,"misc_opp_pts_off_tov":4,"misc_opp_pts_2nd_chance":8,"misc_opp_pts_fb":4,"misc_opp_pts_paint":20,"misc_blk":0,"misc_blka":1,"misc_pf":2,"misc_pfd":1,"scr_pct_2pt_fga":"0.429","scr_pct_pts_2pt":"0.154","scr_pct_pts_2ptmr":"0.154","scr_pct_pts_3pt":"0.692","scr_pct_pts_fb":"0.000","scr_pct_pts_ft":"0.154","scr_pct_pts_off_tov":"0.000","scr_pct_pts_paint":"0.000","scr_pct_pts_ast_2pm":"1.000","scr_pct_pts_ast_3pm":"1.000","scr_pct_pts_ast_fgm":"1.000","usg_pct":"0.186","usg_pct_fgm":"0.211","usg_pct_fga":"0.200","usg_pct_fg3m":"0.375","usg_pct_fg3a":"0.400","usg_pct_ftm":"0.400","usg_pct_fta":"0.333","usg_pct_oreb":"0.333","usg_pct_dreb":"0.222","usg_pct_reb":"0.250","usg_pct_ast":"0.154","usg_pct_stl":"0.200","usg_pct_tov":"0.100","usg_pct_blk":"0.000","usg_pct_blka":"0.250","usg_pct_pf":"0.250","usg_pct_pfd":"0.250","usg_pct_pts":"0.255","four_efg_pct":"0.657","four_fta_rate":"0.171","four_tm_tov_pct":"0.224","four_oreb_pct":"0.214","four_opp_efg_pct":"0.571","four_opp_fta_rate":"0.429","four_opp_tm_tov_pct":"0.241","four_opp_oreb_pct":"0.357"},{"id":47830,"game_id":21401067,"team_id":1610612750,"opponent_id":1610612747,"player_id":203930,"box_minutes":1458,"box_fgm":1,"box_fga":7,"box_fg3m":1,"box_fg3a":6,"box_ftm":2,"box_fta":2,"box_oreb":0,"box_dreb":1,"box_ast":2,"box_stl":1,"box_blk":0,"box_to":0,"box_pf":0,"box_pts":5,"box_plus_minus":9,"trk_speed":"3.77","trk_dist":"1.58","trk_orbc":0,"trk_drbc":1,"trk_touches":21,"trk_sast":0,"trk_ftast":0,"trk_pass":13,"trk_cfgm":1,"trk_cfga":3,"trk_ufgm":0,"trk_ufga":4,"trk_dfgm":0,"trk_dfga":0,"adv_off_rating":"123.6","adv_def_rating":"102.8","adv_ast_pct":"0.100","adv_ast_tov":"0.000","adv_ast_ratio":"20.20","adv_oreb_pct":"0.000","adv_dreb_pct":"0.056","adv_treb_pct":"0.029","adv_tm_tov_pct":"0.0","adv_efg_pct":"0.214","adv_ts_pct":"0.317","adv_usg_pct":"0.158","adv_pace":"95.16","adv_pie":"0.030","misc_pts_off_tov":2,"misc_pts_2nd_chance":0,"misc_pts_fb":5,"misc_pts_paint":0,"misc_opp_pts_off_tov":4,"misc_opp_pts_2nd_chance":11,"misc_opp_pts_fb":2,"misc_opp_pts_paint":22,"misc_blk":0,"misc_blka":0,"misc_pf":0,"misc_pfd":2,"scr_pct_2pt_fga":"0.143","scr_pct_pts_2pt":"0.000","scr_pct_pts_2ptmr":"0.000","scr_pct_pts_3pt":"0.600","scr_pct_pts_fb":"1.000","scr_pct_pts_ft":"0.400","scr_pct_pts_off_tov":"0.400","scr_pct_pts_paint":"0.000","scr_pct_pts_ast_2pm":"0.000","scr_pct_pts_ast_3pm":"1.000","scr_pct_pts_ast_fgm":"1.000","usg_pct":"0.158","usg_pct_fgm":"0.048","usg_pct_fga":"0.189","usg_pct_fg3m":"0.200","usg_pct_fg3a":"0.462","usg_pct_ftm":"0.167","usg_pct_fta":"0.154","usg_pct_oreb":"0.000","usg_pct_dreb":"0.083","usg_pct_reb":"0.071","usg_pct_ast":"0.167","usg_pct_stl":"0.200","usg_pct_tov":"0.000","usg_pct_blk":"0.000","usg_pct_blka":"0.000","usg_pct_pf":"0.000","usg_pct_pfd":"0.200","usg_pct_pts":"0.085","four_efg_pct":"0.635","four_fta_rate":"0.351","four_tm_tov_pct":"0.147","four_oreb_pct":"0.125","four_opp_efg_pct":"0.524","four_opp_fta_rate":"0.143","four_opp_tm_tov_pct":"0.206","four_opp_oreb_pct":"0.333"},{"id":48102,"game_id":21401081,"team_id":1610612750,"opponent_id":1610612745,"player_id":203930,"box_minutes":1032,"box_fgm":2,"box_fga":5,"box_fg3m":0,"box_fg3a":2,"box_ftm":0,"box_fta":0,"box_oreb":0,"box_dreb":1,"box_ast":0,"box_stl":1,"box_blk":0,"box_to":0,"box_pf":1,"box_pts":4,"box_plus_minus":-11,"trk_speed":"4.10","trk_dist":"1.18","trk_orbc":0,"trk_drbc":1,"trk_touches":9,"trk_sast":1,"trk_ftast":1,"trk_pass":4,"trk_cfgm":2,"trk_cfga":3,"trk_ufgm":0,"trk_ufga":2,"trk_dfgm":1,"trk_dfga":1,"adv_off_rating":"82.2","adv_def_rating":"108.5","adv_ast_pct":"0.000","adv_ast_tov":"0.000","adv_ast_ratio":"0.00","adv_oreb_pct":"0.000","adv_dreb_pct":"0.063","adv_treb_pct":"0.034","adv_tm_tov_pct":"0.0","adv_efg_pct":"0.400","adv_ts_pct":"0.400","adv_usg_pct":"0.131","adv_pace":"100.69","adv_pie":"0.036","misc_pts_off_tov":2,"misc_pts_2nd_chance":0,"misc_pts_fb":4,"misc_pts_paint":4,"misc_opp_pts_off_tov":11,"misc_opp_pts_2nd_chance":6,"misc_opp_pts_fb":6,"misc_opp_pts_paint":26,"misc_blk":0,"misc_blka":0,"misc_pf":1,"misc_pfd":0,"scr_pct_2pt_fga":"0.600","scr_pct_pts_2pt":"1.000","scr_pct_pts_2ptmr":"0.000","scr_pct_pts_3pt":"0.000","scr_pct_pts_fb":"1.000","scr_pct_pts_ft":"0.000","scr_pct_pts_off_tov":"0.500","scr_pct_pts_paint":"1.000","scr_pct_pts_ast_2pm":"0.000","scr_pct_pts_ast_3pm":"0.000","scr_pct_pts_ast_fgm":"0.000","usg_pct":"0.131","usg_pct_fgm":"0.222","usg_pct_fga":"0.200","usg_pct_fg3m":"0.000","usg_pct_fg3a":"0.400","usg_pct_ftm":"0.000","usg_pct_fta":"0.000","usg_pct_oreb":"0.000","usg_pct_dreb":"0.111","usg_pct_reb":"0.083","usg_pct_ast":"0.000","usg_pct_stl":"0.500","usg_pct_tov":"0.000","usg_pct_blk":"0.000","usg_pct_blka":"0.000","usg_pct_pf":"0.250","usg_pct_pfd":"0.000","usg_pct_pts":"0.138","four_efg_pct":"0.380","four_fta_rate":"0.480","four_tm_tov_pct":"0.227","four_oreb_pct":"0.231","four_opp_efg_pct":"0.543","four_opp_fta_rate":"0.057","four_opp_tm_tov_pct":"0.217","four_opp_oreb_pct":"0.438"}]