[{"id":6730,"game_id":21300319,"team_id":1610612746,"opponent_id":1610612738,"player_id":1536,"box_minutes":738,"box_fgm":0,"box_fga":3,"box_fg3m":0,"box_fg3a":3,"box_ftm":0,"box_fta":0,"box_oreb":0,"box_dreb":0,"box_ast":0,"box_stl":0,"box_blk":0,"box_to":0,"box_pf":0,"box_pts":0,"box_plus_minus":1,"trk_speed":"3.44","trk_dist":"0.71","trk_orbc":0,"trk_drbc":0,"trk_touches":6,"trk_sast":0,"trk_ftast":0,"trk_pass":3,"trk_cfgm":0,"trk_cfga":1,"trk_ufgm":0,"trk_ufga":2,"trk_dfgm":0,"trk_dfga":0,"adv_off_rating":"90.9","adv_def_rating":"79.4","adv_ast_pct":"0.000","adv_ast_tov":"0.000","adv_ast_ratio":"0.00","adv_oreb_pct":"0.000","adv_dreb_pct":"0.000","adv_treb_pct":"0.000","adv_tm_tov_pct":"0.0","adv_efg_pct":"0.000","adv_ts_pct":"0.000","adv_usg_pct":"0.115","adv_pace":"98.81","adv_pie":"-0.100","misc_pts_off_tov":0,"misc_pts_2nd_chance":0,"misc_pts_fb":0,"misc_pts_paint":0,"misc_opp_pts_off_tov":6,"misc_opp_pts_2nd_chance":2,"misc_opp_pts_fb":2,"misc_opp_pts_paint":8,"misc_blk":0,"misc_blka":0,"misc_pf":0,"misc_pfd":1,"scr_pct_2pt_fga":"0.000","scr_pct_pts_2pt":"0.000","scr_pct_pts_2ptmr":"0.000","scr_pct_pts_3pt":"0.000","scr_pct_pts_fb":"0.000","scr_pct_pts_ft":"0.000","scr_pct_pts_off_tov":"0.000","scr_pct_pts_paint":"0.000","scr_pct_pts_ast_2pm":"0.000","scr_pct_pts_ast_3pm":"0.000","scr_pct_pts_ast_fgm":"0.000","usg_pct":"0.115","usg_pct_fgm":"0.000","usg_pct_fga":"0.150","usg_pct_fg3m":"0.000","usg_pct_fg3a":"0.600","usg_pct_ftm":"0.000","usg_pct_fta":"0.000","usg_pct_oreb":"0.000","usg_pct_dreb":"0.000","usg_pct_reb":"0.000","usg_pct_ast":"0.000","usg_pct_stl":"0.000","usg_pct_tov":"0.000","usg_pct_blk":"0.000","usg_pct_blka":"0.000","usg_pct_pf":"0.000","usg_pct_pfd":"0.250","usg_pct_pts":"0.000","four_efg_pct":"0.475","four_fta_rate":"0.250","four_tm_tov_pct":"0.165","four_oreb_pct":"0.200","four_opp_efg_pct":"0.476","four_opp_fta_rate":"0.048","four_opp_tm_tov_pct":"0.265","four_opp_oreb_pct":"0.286"},{"id":6893,"game_id":21300327,"team_id":1610612746,"opponent_id":1610612751,"player_id":1536,"box_minutes":1372,"box_fgm":1,"box_fga":5,"box_fg3m":0,"box_fg3a":3,"box_ftm":1,"box_fta":2,"box_oreb":1,"box_dreb":2,"box_ast":1,"box_stl":2,"box_blk":0,"box_to":0,"box_pf":2,"box_pts":3,"box_plus_minus":-3,"trk_speed":"3.56","trk_dist":"1.37","trk_orbc":1,"trk_drbc":2,"trk_touches":15,"trk_sast":0,"trk_ftast":0,"trk_pass":9,"trk_cfgm":1,"trk_cfga":3,"trk_ufgm":0,"trk_ufga":2,"trk_dfgm":0,"trk_dfga":0,"adv_off_rating":"101.2","adv_def_rating":"105.2","adv_ast_pct":"0.083","adv_ast_tov":"0.000","adv_ast_ratio":"14.50","adv_oreb_pct":"0.048","adv_dreb_pct":"0.154","adv_treb_pct":"0.088","adv_tm_tov_pct":"0.0","adv_efg_pct":"0.200","adv_ts_pct":"0.255","adv_usg_pct":"0.117","adv_pace":"96.60","adv_pie":"0.024","misc_pts_off_tov":0,"misc_pts_2nd_chance":2,"misc_pts_fb":1,"misc_pts_paint":2,"misc_opp_pts_off_tov":11,"misc_opp_pts_2nd_chance":0,"misc_opp_pts_fb":4,"misc_opp_pts_paint":10,"misc_blk":0,"misc_blka":0,"misc_pf":2,"misc_pfd":2,"scr_pct_2pt_fga":"0.400","scr_pct_pts_2pt":"0.667","scr_pct_pts_2ptmr":"0.000","scr_pct_pts_3pt":"0.000","scr_pct_pts_fb":"0.333","scr_pct_pts_ft":"0.333","scr_pct_pts_off_tov":"0.000","scr_pct_pts_paint":"0.667","scr_pct_pts_ast_2pm":"0.000","scr_pct_pts_ast_3pm":"0.000","scr_pct_pts_ast_fgm":"0.000","usg_pct":"0.117","usg_pct_fgm":"0.077","usg_pct_fga":"0.156","usg_pct_fg3m":"0.000","usg_pct_fg3a":"0.300","usg_pct_ftm":"0.056","usg_pct_fta":"0.077","usg_pct_oreb":"0.200","usg_pct_dreb":"0.167","usg_pct_reb":"0.176","usg_pct_ast":"0.143","usg_pct_stl":"0.500","usg_pct_tov":"0.000","usg_pct_blk":"0.000","usg_pct_blka":"0.000","usg_pct_pf":"0.182","usg_pct_pfd":"0.133","usg_pct_pts":"0.065","four_efg_pct":"0.438","four_fta_rate":"0.813","four_tm_tov_pct":"0.154","four_oreb_pct":"0.238","four_opp_efg_pct":"0.547","four_opp_fta_rate":"0.469","four_opp_tm_tov_pct":"0.193","four_opp_oreb_pct":"0.077"},{"id":7212,"game_id":21300343,"team_id":1610612746,"opponent_id":1610612764,"player_id":1536,"box_minutes":477,"box_fgm":0,"box_fga":0,"box_fg3m":0,"box_fg3a":0,"box_ftm":1,"box_fta":2,"box_oreb":0,"box_dreb":3,"box_ast":1,"box_stl":1,"box_blk":0,"box_to":2,"box_pf":1,"box_pts":1,"box_plus_minus":1,"trk_speed":"3.82","trk_dist":"0.51","trk_orbc":0,"trk_drbc":3,"trk_touches":10,"trk_sast":0,"trk_ftast":0,"trk_pass":7,"trk_cfgm":0,"trk_cfga":0,"trk_ufgm":0,"trk_ufga":0,"trk_dfgm":0,"trk_dfga":0,"adv_off_rating":"103.8","adv_def_rating":"85.7","adv_ast_pct":"0.333","adv_ast_tov":"0.500","adv_ast_ratio":"25.80","adv_oreb_pct":"0.000","adv_dreb_pct":"0.500","adv_treb_pct":"0.300","adv_tm_tov_pct":"51.5","adv_efg_pct":"0.000","adv_ts_pct":"0.568","adv_usg_pct":"0.230","adv_pace":"80.06","adv_pie":"0.148","misc_pts_off_tov":0,"misc_pts_2nd_chance":0,"misc_pts_fb":0,"misc_pts_paint":0,"misc_opp_pts_off_tov":5,"misc_opp_pts_2nd_chance":2,"misc_opp_pts_fb":2,"misc_opp_pts_paint":4,"misc_blk":0,"misc_blka":0,"misc_pf":1,"misc_pfd":2,"scr_pct_2pt_fga":"0.000","scr_pct_pts_2pt":"0.000","scr_pct_pts_2ptmr":"0.000","scr_pct_pts_3pt":"0.000","scr_pct_pts_fb":"0.000","scr_pct_pts_ft":"1.000","scr_pct_pts_off_tov":"0.000","scr_pct_pts_paint":"0.000","scr_pct_pts_ast_2pm":"0.000","scr_pct_pts_ast_3pm":"0.000","scr_pct_pts_ast_fgm":"0.000","usg_pct":"0.230","usg_pct_fgm":"0.000","usg_pct_fga":"0.000","usg_pct_fg3m":"0.000","usg_pct_fg3a":"0.000","usg_pct_ftm":"0.167","usg_pct_fta":"0.250","usg_pct_oreb":"0.000","usg_pct_dreb":"0.600","usg_pct_reb":"0.600","usg_pct_ast":"0.500","usg_pct_stl":"0.500","usg_pct_tov":"0.667","usg_pct_blk":"0.000","usg_pct_blka":"0.000","usg_pct_pf":"0.250","usg_pct_pfd":"0.286","usg_pct_pts":"0.077","four_efg_pct":"0.583","four_fta_rate":"1.333","four_tm_tov_pct":"0.240","four_oreb_pct":"0.000","four_opp_efg_pct":"0.500","four_opp_fta_rate":"0.000","four_opp_tm_tov_pct":"0.214","four_opp_oreb_pct":"0.167"},{"id":7668,"game_id":21300363,"team_id":1610612746,"opponent_id":1610612759,"player_id":1536,"box_minutes":1014,"box_fgm":3,"box_fga":5,"box_fg3m":0,"box_fg3a":1,"box_ftm":0,"box_fta":0,"box_oreb":0,"box_dreb":0,"box_ast":0,"box_stl":0,"box_blk":0,"box_to":1,"box_pf":2,"box_pts":6,"box_plus_minus":21,"trk_speed":"3.82","trk_dist":"1.08","trk_orbc":0,"trk_drbc":4,"trk_touches":17,"trk_sast":0,"trk_ftast":0,"trk_pass":11,"trk_cfgm":3,"trk_cfga":5,"trk_ufgm":0,"trk_ufga":0,"trk_dfgm":0,"trk_dfga":0,"adv_off_rating":"114.2","adv_def_rating":"63.3","adv_ast_pct":"0.000","adv_ast_tov":"0.000","adv_ast_ratio":"0.00","adv_oreb_pct":"0.000","adv_dreb_pct":"0.000","adv_treb_pct":"0.000","adv_tm_tov_pct":"16.7","adv_efg_pct":"0.600","adv_ts_pct":"0.600","adv_usg_pct":"0.144","adv_pace":"102.82","adv_pie":"0.021","misc_pts_off_tov":4,"misc_pts_2nd_chance":0,"misc_pts_fb":0,"misc_pts_paint":4,"misc_opp_pts_off_tov":4,"misc_opp_pts_2nd_chance":0,"misc_opp_pts_fb":3,"misc_opp_pts_paint":8,"misc_blk":0,"misc_blka":0,"misc_pf":2,"misc_pfd":0,"scr_pct_2pt_fga":"0.800","scr_pct_pts_2pt":"1.000","scr_pct_pts_2ptmr":"0.333","scr_pct_pts_3pt":"0.000","scr_pct_pts_fb":"0.000","scr_pct_pts_ft":"0.000","scr_pct_pts_off_tov":"0.667","scr_pct_pts_paint":"0.667","scr_pct_pts_ast_2pm":"0.333","scr_pct_pts_ast_3pm":"0.000","scr_pct_pts_ast_fgm":"0.333","usg_pct":"0.144","usg_pct_fgm":"0.176","usg_pct_fga":"0.167","usg_pct_fg3m":"0.000","usg_pct_fg3a":"0.167","usg_pct_ftm":"0.000","usg_pct_fta":"0.000","usg_pct_oreb":"0.000","usg_pct_dreb":"0.000","usg_pct_reb":"0.000","usg_pct_ast":"0.000","usg_pct_stl":"0.000","usg_pct_tov":"0.111","usg_pct_blk":"0.000","usg_pct_blka":"0.000","usg_pct_pf":"0.400","usg_pct_pfd":"0.000","usg_pct_pts":"0.140","four_efg_pct":"0.633","four_fta_rate":"0.200","four_tm_tov_pct":"0.239","four_oreb_pct":"0.364","four_opp_efg_pct":"0.452","four_opp_fta_rate":"0.190","four_opp_tm_tov_pct":"0.374","four_opp_oreb_pct":"0.067"},{"id":8013,"game_id":21300380,"team_id":1610612746,"opponent_id":1610612740,"player_id":1536,"box_minutes":621,"box_fgm":0,"box_fga":4,"box_fg3m":0,"box_fg3a":2,"box_ftm":0,"box_fta":0,"box_oreb":0,"box_dreb":0,"box_ast":0,"box_stl":1,"box_blk":1,"box_to":0,"box_pf":1,"box_pts":0,"box_plus_minus":6,"trk_speed":"4.16","trk_dist":"0.72","trk_orbc":0,"trk_drbc":1,"trk_touches":9,"trk_sast":0,"trk_ftast":0,"trk_pass":5,"trk_cfgm":0,"trk_cfga":1,"trk_ufgm":0,"trk_ufga":3,"trk_dfgm":0,"trk_dfga":2,"adv_off_rating":"117.8","adv_def_rating":"89.5","adv_ast_pct":"0.000","adv_ast_tov":"0.000","adv_ast_ratio":"0.00","adv_oreb_pct":"0.000","adv_dreb_pct":"0.000","adv_treb_pct":"0.000","adv_tm_tov_pct":"0.0","adv_efg_pct":"0.000","adv_ts_pct":"0.000","adv_usg_pct":"0.186","adv_pace":"89.32","adv_pie":"-0.084","misc_pts_off_tov":0,"misc_pts_2nd_chance":0,"misc_pts_fb":0,"misc_pts_paint":0,"misc_opp_pts_off_tov":0,"misc_opp_pts_2nd_chance":0,"misc_opp_pts_fb":0,"misc_opp_pts_paint":6,"misc_blk":1,"misc_blka":0,"misc_pf":1,"misc_pfd":0,"scr_pct_2pt_fga":"0.500","scr_pct_pts_2pt":"0.000","scr_pct_pts_2ptmr":"0.000","scr_pct_pts_3pt":"0.000","scr_pct_pts_fb":"0.000","scr_pct_pts_ft":"0.000","scr_pct_pts_off_tov":"0.000","scr_pct_pts_paint":"0.000","scr_pct_pts_ast_2pm":"0.000","scr_pct_pts_ast_3pm":"0.000","scr_pct_pts_ast_fgm":"0.000","usg_pct":"0.186","usg_pct_fgm":"0.000","usg_pct_fga":"0.222","usg_pct_fg3m":"0.000","usg_pct_fg3a":"0.286","usg_pct_ftm":"0.000","usg_pct_fta":"0.000","usg_pct_oreb":"0.000","usg_pct_dreb":"0.000","usg_pct_reb":"0.000","usg_pct_ast":"0.000","usg_pct_stl":"0.500","usg_pct_tov":"0.000","usg_pct_blk":"0.333","usg_pct_blka":"0.000","usg_pct_pf":"1.000","usg_pct_pfd":"0.000","usg_pct_pts":"0.000","four_efg_pct":"0.417","four_fta_rate":"0.444","four_tm_tov_pct":"0.000","four_oreb_pct":"0.167","four_opp_efg_pct":"0.425","four_opp_fta_rate":"0.000","four_opp_tm_tov_pct":"0.158","four_opp_oreb_pct":"0.308"},{"id":8500,"game_id":21300403,"team_id":1610612746,"opponent_id":1610612743,"player_id":1536,"box_minutes":186,"box_fgm":0,"box_fga":0,"box_fg3m":0,"box_fg3a":0,"box_ftm":0,"box_fta":0,"box_oreb":0,"box_dreb":0,"box_ast":1,"box_stl":1,"box_blk":0,"box_to":1,"box_pf":1,"box_pts":0,"box_plus_minus":0,"trk_speed":"0.00","trk_dist":"0.00","trk_orbc":0,"trk_drbc":0,"trk_touches":0,"trk_sast":0,"trk_ftast":0,"trk_pass":0,"trk_cfgm":0,"trk_cfga":0,"trk_ufgm":0,"trk_ufga":0,"trk_dfgm":0,"trk_dfga":0,"adv_off_rating":"159.9","adv_def_rating":"159.9","adv_ast_pct":"0.250","adv_ast_tov":"1.000","adv_ast_ratio":"50.00","adv_oreb_pct":"0.000","adv_dreb_pct":"0.000","adv_treb_pct":"0.000","adv_tm_tov_pct":"50.0","adv_efg_pct":"0.000","adv_ts_pct":"0.000","adv_usg_pct":"0.145","adv_pace":"106.47","adv_pie":"0.000","misc_pts_off_tov":0,"misc_pts_2nd_chance":0,"misc_pts_fb":0,"misc_pts_paint":0,"misc_opp_pts_off_tov":2,"misc_opp_pts_2nd_chance":2,"misc_opp_pts_fb":2,"misc_opp_pts_paint":4,"misc_blk":0,"misc_blka":0,"misc_pf":1,"misc_pfd":0,"scr_pct_2pt_fga":"0.000","scr_pct_pts_2pt":"0.000","scr_pct_pts_2ptmr":"0.000","scr_pct_pts_3pt":"0.000","scr_pct_pts_fb":"0.000","scr_pct_pts_ft":"0.000","scr_pct_pts_off_tov":"0.000","scr_pct_pts_paint":"0.000","scr_pct_pts_ast_2pm":"0.000","scr_pct_pts_ast_3pm":"0.000","scr_pct_pts_ast_fgm":"0.000","usg_pct":"0.145","usg_pct_fgm":"0.000","usg_pct_fga":"0.000","usg_pct_fg3m":"0.000","usg_pct_fg3a":"0.000","usg_pct_ftm":"0.000","usg_pct_fta":"0.000","usg_pct_oreb":"0.000","usg_pct_dreb":"0.000","usg_pct_reb":"0.000","usg_pct_ast":"0.333","usg_pct_stl":"0.500","usg_pct_tov":"1.000","usg_pct_blk":"0.000","usg_pct_blka":"0.000","usg_pct_pf":"1.000","usg_pct_pfd":"0.000","usg_pct_pts":"0.000","four_efg_pct":"1.000","four_fta_rate":"0.400","four_tm_tov_pct":"0.145","four_oreb_pct":"0.000","four_opp_efg_pct":"0.900","four_opp_fta_rate":"0.400","four_opp_tm_tov_pct":"0.291","four_opp_oreb_pct":"1.000"},{"id":9433,"game_id":21300447,"team_id":1610612746,"opponent_id":1610612762,"player_id":1536,"box_minutes":830,"box_fgm":0,"box_fga":1,"box_fg3m":0,"box_fg3a":1,"box_ftm":0,"box_fta":0,"box_oreb":1,"box_dreb":1,"box_ast":1,"box_stl":0,"box_blk":0,"box_to":0,"box_pf":1,"box_pts":0,"box_plus_minus":5,"trk_speed":"3.74","trk_dist":"0.87","trk_orbc":1,"trk_drbc":3,"trk_touches":17,"trk_sast":0,"trk_ftast":0,"trk_pass":14,"trk_cfgm":0,"trk_cfga":1,"trk_ufgm":0,"trk_ufga":0,"trk_dfgm":1,"trk_dfga":3,"adv_off_rating":"114.0","adv_def_rating":"101.7","adv_ast_pct":"0.083","adv_ast_tov":"0.000","adv_ast_ratio":"50.00","adv_oreb_pct":"0.071","adv_dreb_pct":"0.111","adv_treb_pct":"0.087","adv_tm_tov_pct":"0.0","adv_efg_pct":"0.000","adv_ts_pct":"0.000","adv_usg_pct":"0.030","adv_pace":"97.99","adv_pie":"0.010","misc_pts_off_tov":0,"misc_pts_2nd_chance":0,"misc_pts_fb":0,"misc_pts_paint":0,"misc_opp_pts_off_tov":0,"misc_opp_pts_2nd_chance":3,"misc_opp_pts_fb":0,"misc_opp_pts_paint":10,"misc_blk":0,"misc_blka":0,"misc_pf":1,"misc_pfd":2,"scr_pct_2pt_fga":"0.000","scr_pct_pts_2pt":"0.000","scr_pct_pts_2ptmr":"0.000","scr_pct_pts_3pt":"0.000","scr_pct_pts_fb":"0.000","scr_pct_pts_ft":"0.000","scr_pct_pts_off_tov":"0.000","scr_pct_pts_paint":"0.000","scr_pct_pts_ast_2pm":"0.000","scr_pct_pts_ast_3pm":"0.000","scr_pct_pts_ast_fgm":"0.000","usg_pct":"0.030","usg_pct_fgm":"0.000","usg_pct_fga":"0.037","usg_pct_fg3m":"0.000","usg_pct_fg3a":"0.200","usg_pct_ftm":"0.000","usg_pct_fta":"0.000","usg_pct_oreb":"0.250","usg_pct_dreb":"0.143","usg_pct_reb":"0.182","usg_pct_ast":"0.167","usg_pct_stl":"0.000","usg_pct_tov":"0.000","usg_pct_blk":"0.000","usg_pct_blka":"0.000","usg_pct_pf":"0.167","usg_pct_pfd":"0.250","usg_pct_pts":"0.000","four_efg_pct":"0.463","four_fta_rate":"0.333","four_tm_tov_pct":"0.069","four_oreb_pct":"0.286","four_opp_efg_pct":"0.553","four_opp_fta_rate":"0.421","four_opp_tm_tov_pct":"0.254","four_opp_oreb_pct":"0.222"},{"id":9680,"game_id":21300459,"team_id":1610612746,"opponent_id":1610612756,"player_id":1536,"box_minutes":840,"box_fgm":2,"box_fga":8,"box_fg3m":1,"box_fg3a":4,"box_ftm":0,"box_fta":0,"box_oreb":0,"box_dreb":2,"box_ast":1,"box_stl":1,"box_blk":0,"box_to":1,"box_pf":2,"box_pts":5,"box_plus_minus":9,"trk_speed":"3.78","trk_dist":"0.89","trk_orbc":0,"trk_drbc":5,"trk_touches":29,"trk_sast":1,"trk_ftast":0,"trk_pass":20,"trk_cfgm":1,"trk_cfga":6,"trk_ufgm":1,"trk_ufga":2,"trk_dfgm":0,"trk_dfga":0,"adv_off_rating":"109.7","adv_def_rating":"80.6","adv_ast_pct":"0.111","adv_ast_tov":"1.000","adv_ast_ratio":"10.00","adv_oreb_pct":"0.000","adv_dreb_pct":"0.154","adv_treb_pct":"0.080","adv_tm_tov_pct":"10.0","adv_efg_pct":"0.313","adv_ts_pct":"0.313","adv_usg_pct":"0.264","adv_pace":"102.58","adv_pie":"0.000","misc_pts_off_tov":2,"misc_pts_2nd_chance":0,"misc_pts_fb":2,"misc_pts_paint":2,"misc_opp_pts_off_tov":4,"misc_opp_pts_2nd_chance":0,"misc_opp_pts_fb":2,"misc_opp_pts_paint":10,"misc_blk":0,"misc_blka":0,"misc_pf":2,"misc_pfd":0,"scr_pct_2pt_fga":"0.500","scr_pct_pts_2pt":"0.400","scr_pct_pts_2ptmr":"0.000","scr_pct_pts_3pt":"0.600","scr_pct_pts_fb":"0.400","scr_pct_pts_ft":"0.000","scr_pct_pts_off_tov":"0.400","scr_pct_pts_paint":"0.400","scr_pct_pts_ast_2pm":"1.000","scr_pct_pts_ast_3pm":"1.000","scr_pct_pts_ast_fgm":"1.000","usg_pct":"0.264","usg_pct_fgm":"0.182","usg_pct_fga":"0.333","usg_pct_fg3m":"0.250","usg_pct_fg3a":"0.444","usg_pct_ftm":"0.000","usg_pct_fta":"0.000","usg_pct_oreb":"0.000","usg_pct_dreb":"0.182","usg_pct_reb":"0.133","usg_pct_ast":"0.143","usg_pct_stl":"0.250","usg_pct_tov":"0.143","usg_pct_blk":"0.000","usg_pct_blka":"0.000","usg_pct_pf":"0.333","usg_pct_pfd":"0.000","usg_pct_pts":"0.152","four_efg_pct":"0.542","four_fta_rate":"0.292","four_tm_tov_pct":"0.233","four_oreb_pct":"0.333","four_opp_efg_pct":"0.500","four_opp_fta_rate":"0.182","four_opp_tm_tov_pct":"0.269","four_opp_oreb_pct":"0.154"},{"id":10390,"game_id":21300494,"team_id":1610612746,"opponent_id":1610612759,"player_id":1536,"box_minutes":329,"box_fgm":0,"box_fga":0,"box_fg3m":0,"box_fg3a":0,"box_ftm":0,"box_fta":0,"box_oreb":0,"box_dreb":0,"box_ast":0,"box_stl":0,"box_blk":0,"box_to":1,"box_pf":1,"box_pts":0,"box_plus_minus":-15,"trk_speed":"0.00","trk_dist":"0.00","trk_orbc":0,"trk_drbc":0,"trk_touches":0,"trk_sast":0,"trk_ftast":0,"trk_pass":0,"trk_cfgm":0,"trk_cfga":0,"trk_ufgm":0,"trk_ufga":0,"trk_dfgm":0,"trk_dfga":0,"adv_off_rating":"18.2","adv_def_rating":"158.0","adv_ast_pct":"0.000","adv_ast_tov":"0.000","adv_ast_ratio":"0.00","adv_oreb_pct":"0.000","adv_dreb_pct":"0.000","adv_treb_pct":"0.000","adv_tm_tov_pct":"99.9","adv_efg_pct":"0.000","adv_ts_pct":"0.000","adv_usg_pct":"0.091","adv_pace":"95.24","adv_pie":"-0.190","misc_pts_off_tov":0,"misc_pts_2nd_chance":0,"misc_pts_fb":0,"misc_pts_paint":0,"misc_opp_pts_off_tov":7,"misc_opp_pts_2nd_chance":7,"misc_opp_pts_fb":0,"misc_opp_pts_paint":8,"misc_blk":0,"misc_blka":0,"misc_pf":1,"misc_pfd":0,"scr_pct_2pt_fga":"0.000","scr_pct_pts_2pt":"0.000","scr_pct_pts_2ptmr":"0.000","scr_pct_pts_3pt":"0.000","scr_pct_pts_fb":"0.000","scr_pct_pts_ft":"0.000","scr_pct_pts_off_tov":"0.000","scr_pct_pts_paint":"0.000","scr_pct_pts_ast_2pm":"0.000","scr_pct_pts_ast_3pm":"0.000","scr_pct_pts_ast_fgm":"0.000","usg_pct":"0.091","usg_pct_fgm":"0.000","usg_pct_fga":"0.000","usg_pct_fg3m":"0.000","usg_pct_fg3a":"0.000","usg_pct_ftm":"0.000","usg_pct_fta":"0.000","usg_pct_oreb":"0.000","usg_pct_dreb":"0.000","usg_pct_reb":"0.000","usg_pct_ast":"0.000","usg_pct_stl":"0.000","usg_pct_tov":"0.167","usg_pct_blk":"0.000","usg_pct_blka":"0.000","usg_pct_pf":"0.200","usg_pct_pfd":"0.000","usg_pct_pts":"0.000","four_efg_pct":"0.200","four_fta_rate":"0.000","four_tm_tov_pct":"0.545","four_oreb_pct":"0.000","four_opp_efg_pct":"0.636","four_opp_fta_rate":"0.364","four_opp_tm_tov_pct":"0.000","four_opp_oreb_pct":"0.500"}]